{
  "0.0.1": {
    "type": "tarball",
    "url": "https://registry.npmjs.org/@types/d3-array/-/d3-array-0.0.1.tgz",
    "narHash": "sha256-PZmnUoEums33aLic+MvMTtAQuJFlRp94cTbWr07h89w="
  },
  "0.0.2": {
    "type": "tarball",
    "url": "https://registry.npmjs.org/@types/d3-array/-/d3-array-0.0.2.tgz",
    "narHash": "sha256-PyTVzlYeOY/HthJp3VqDQ7m45JTHgUgX2BqxOVe2keI="
  },
  "0.0.3": {
    "type": "tarball",
    "url": "https://registry.npmjs.org/@types/d3-array/-/d3-array-0.0.3.tgz",
    "narHash": "sha256-Egfb4wuvNIDpxnaZ10nzVhPGWXxNUPmQKry2/76coYo="
  },
  "1.0.4": {
    "type": "tarball",
    "url": "https://registry.npmjs.org/@types/d3-array/-/d3-array-1.0.4.tgz",
    "narHash": "sha256-FTL4GNHpr53zZB6iMDzJJO9C4N1uRUwRVf5JwvIB77s="
  },
  "1.0.5": {
    "type": "tarball",
    "url": "https://registry.npmjs.org/@types/d3-array/-/d3-array-1.0.5.tgz",
    "narHash": "sha256-MX/ue2RE9THJ6Qa00KN3oDzJD6UjNFIk1bwXwoeO7es="
  },
  "1.0.6": {
    "type": "tarball",
    "url": "https://registry.npmjs.org/@types/d3-array/-/d3-array-1.0.6.tgz",
    "narHash": "sha256-LeVhxrLsR162qYCUZGo4lrS7jNTtKFF08b2fHavH5zw="
  },
  "1.0.7": {
    "type": "tarball",
    "url": "https://registry.npmjs.org/@types/d3-array/-/d3-array-1.0.7.tgz",
    "narHash": "sha256-jrsAWMNaH/JE7tqj5XXrd3hvOkuZP1km5fVMHhHz3XM="
  },
  "1.0.8": {
    "type": "tarball",
    "url": "https://registry.npmjs.org/@types/d3-array/-/d3-array-1.0.8.tgz",
    "narHash": "sha256-z2yFpcUfiRyOK9m5VV7R9I4v6j3ByFGFDIZ/OdNj+4g="
  },
  "1.1.0": {
    "type": "tarball",
    "url": "https://registry.npmjs.org/@types/d3-array/-/d3-array-1.1.0.tgz",
    "narHash": "sha256-LZH1wubD/KgAjAPK10VP2gXBzV6FZDAUYxu9GQrUgDI="
  },
  "1.1.1": {
    "type": "tarball",
    "url": "https://registry.npmjs.org/@types/d3-array/-/d3-array-1.1.1.tgz",
    "narHash": "sha256-jiuRrBaB/YA554YcfT2RyXlvD+a+SJkHuS3Ye8hBY70="
  },
  "1.1.2": {
    "type": "tarball",
    "url": "https://registry.npmjs.org/@types/d3-array/-/d3-array-1.1.2.tgz",
    "narHash": "sha256-FVcICgD+PHxdUhqInrbXj0Soaj11PdCXrkQKPihn64Y="
  },
  "1.1.3": {
    "type": "tarball",
    "url": "https://registry.npmjs.org/@types/d3-array/-/d3-array-1.1.3.tgz",
    "narHash": "sha256-SnvQVBKsDaf3DqlchZh8vV6FL6zv3fRyqf0mOr7G2eI="
  },
  "1.2.0": {
    "type": "tarball",
    "url": "https://registry.npmjs.org/@types/d3-array/-/d3-array-1.2.0.tgz",
    "narHash": "sha256-dO9Hpdjl27YztF55+nKA8o/4GeNkLu/8h4GLUHNRdUc="
  },
  "1.2.1": {
    "type": "tarball",
    "url": "https://registry.npmjs.org/@types/d3-array/-/d3-array-1.2.1.tgz",
    "narHash": "sha256-p++8GwUVS2fnfUVU9M1Eu2yhGbAru1xVSZ2Dn124eZw="
  },
  "1.2.2": {
    "type": "tarball",
    "url": "https://registry.npmjs.org/@types/d3-array/-/d3-array-1.2.2.tgz",
    "narHash": "sha256-z/mwcFBxaIJicYnuBumD7xcQbOGa4AruKdo13tEPfxI="
  },
  "1.2.3": {
    "type": "tarball",
    "url": "https://registry.npmjs.org/@types/d3-array/-/d3-array-1.2.3.tgz",
    "narHash": "sha256-uoMDAJ/tr/SIZ0Txy4dYyRlUPNkQbBioVmJQWxtMmfc="
  },
  "1.2.4": {
    "type": "tarball",
    "url": "https://registry.npmjs.org/@types/d3-array/-/d3-array-1.2.4.tgz",
    "narHash": "sha256-B/0nRTeTI08nCSKeKzbXovVebHHADYbToC33B8pJDCI="
  },
  "1.2.5": {
    "type": "tarball",
    "url": "https://registry.npmjs.org/@types/d3-array/-/d3-array-1.2.5.tgz",
    "narHash": "sha256-dDt4U2Kpice8j4PLXro1vf4VMiGm/ce3NbeSSEMtpRs="
  },
  "1.2.6": {
    "type": "tarball",
    "url": "https://registry.npmjs.org/@types/d3-array/-/d3-array-1.2.6.tgz",
    "narHash": "sha256-GQvvcL97F+E8/Qp9nTC0uYJv/48uT5FGmIRRHjoDRMo="
  },
  "1.2.7": {
    "type": "tarball",
    "url": "https://registry.npmjs.org/@types/d3-array/-/d3-array-1.2.7.tgz",
    "narHash": "sha256-ksu0ShbNold6e2fk7hI8NTR1qt9MvCBhikWB2YClOjA="
  },
  "1.2.8": {
    "type": "tarball",
    "url": "https://registry.npmjs.org/@types/d3-array/-/d3-array-1.2.8.tgz",
    "narHash": "sha256-BBCF6yd/5NeWtIYchA/ys78gixnPS4Z6dZqS/6U/DiA="
  },
  "1.2.9": {
    "type": "tarball",
    "url": "https://registry.npmjs.org/@types/d3-array/-/d3-array-1.2.9.tgz",
    "narHash": "sha256-0p4cBRkz78wTvALXX6V6/F8Ah8bsQGgT3AFq/vgjMtg="
  },
  "2.0.0": {
    "type": "tarball",
    "url": "https://registry.npmjs.org/@types/d3-array/-/d3-array-2.0.0.tgz",
    "narHash": "sha256-RKW2c5zP7xPZs3FjfNGcvwIQp+C8pNjjVBqOT62kBcM="
  },
  "2.1.0": {
    "type": "tarball",
    "url": "https://registry.npmjs.org/@types/d3-array/-/d3-array-2.1.0.tgz",
    "narHash": "sha256-n1vXuHlD/nWo2/2RW2ZatxVdJJodO+LZmTabx7txbso="
  },
  "2.10.0": {
    "type": "tarball",
    "url": "https://registry.npmjs.org/@types/d3-array/-/d3-array-2.10.0.tgz",
    "narHash": "sha256-T72nXbM/i6VoTtzKdvzRfesIDpFak5MxX23mH6PQOgA="
  },
  "2.11.0": {
    "type": "tarball",
    "url": "https://registry.npmjs.org/@types/d3-array/-/d3-array-2.11.0.tgz",
    "narHash": "sha256-r2w2w4ltezU3lHAqkgi4rbWDitAk9/dpN4qvEPSV4gw="
  },
  "2.12.0": {
    "type": "tarball",
    "url": "https://registry.npmjs.org/@types/d3-array/-/d3-array-2.12.0.tgz",
    "narHash": "sha256-kGvTn+LsqyzFKSTu7bDj7aVYPQksR7/dBdtT+lFhaG4="
  },
  "2.12.1": {
    "type": "tarball",
    "url": "https://registry.npmjs.org/@types/d3-array/-/d3-array-2.12.1.tgz",
    "narHash": "sha256-w/NA/tR2ERSJhAw30OF0HwvCpfClIdXsnvOiuj9MXbw="
  },
  "2.12.2": {
    "type": "tarball",
    "url": "https://registry.npmjs.org/@types/d3-array/-/d3-array-2.12.2.tgz",
    "narHash": "sha256-gUG04QRE5yt2oWRSwXaXWjpqRB0RJ/m8mTs31UEjUPE="
  },
  "2.12.3": {
    "type": "tarball",
    "url": "https://registry.npmjs.org/@types/d3-array/-/d3-array-2.12.3.tgz",
    "narHash": "sha256-lmuCrXPtUSjKH26iqEJPwIZhxtwc0yPfPjxlxOdBXjE="
  },
  "2.2.0": {
    "type": "tarball",
    "url": "https://registry.npmjs.org/@types/d3-array/-/d3-array-2.2.0.tgz",
    "narHash": "sha256-F/4ltMg7dzK3zuEwCmPxEE60QCoEvhOSOF9N0tpZ1kw="
  },
  "2.3.0": {
    "type": "tarball",
    "url": "https://registry.npmjs.org/@types/d3-array/-/d3-array-2.3.0.tgz",
    "narHash": "sha256-MZQ4evqPphSGIqh9wpM8u/8IQtfW7MzeRILrx1jV1Ao="
  },
  "2.4.0": {
    "type": "tarball",
    "url": "https://registry.npmjs.org/@types/d3-array/-/d3-array-2.4.0.tgz",
    "narHash": "sha256-/28oaTBcd7nDt/ZTnQQ/SkmnhbX9vIXqciW8ZxLLMLE="
  },
  "2.5.0": {
    "type": "tarball",
    "url": "https://registry.npmjs.org/@types/d3-array/-/d3-array-2.5.0.tgz",
    "narHash": "sha256-nPqS2wHWLd8eCYwUCJL+La5s3v9Hwo77QJ1obi1iVGo="
  },
  "2.5.1": {
    "type": "tarball",
    "url": "https://registry.npmjs.org/@types/d3-array/-/d3-array-2.5.1.tgz",
    "narHash": "sha256-Qrs2Bbmbhqqztlo+ULxTJU1NwSlP0kQmCCjMwPM27mI="
  },
  "2.7.0": {
    "type": "tarball",
    "url": "https://registry.npmjs.org/@types/d3-array/-/d3-array-2.7.0.tgz",
    "narHash": "sha256-l5b09G20YXb+Zc3yOKf0B4tFAQxU1j5lHNvmbX8t4/o="
  },
  "2.8.0": {
    "type": "tarball",
    "url": "https://registry.npmjs.org/@types/d3-array/-/d3-array-2.8.0.tgz",
    "narHash": "sha256-UlDkzdVNdBRfac8z5tP+fYD8AksSZij94/Mzh8uBNGA="
  },
  "2.9.0": {
    "type": "tarball",
    "url": "https://registry.npmjs.org/@types/d3-array/-/d3-array-2.9.0.tgz",
    "narHash": "sha256-J2kDlmjECjxlGIM7aMpnj1U+77sgZlNdHiSI14l0tns="
  },
  "3.0.0": {
    "type": "tarball",
    "url": "https://registry.npmjs.org/@types/d3-array/-/d3-array-3.0.0.tgz",
    "narHash": "sha256-tmPQdRVYv0eeCxoJaCNRDS763zDvtC9A+0B5yvSuPbs="
  },
  "3.0.1": {
    "type": "tarball",
    "url": "https://registry.npmjs.org/@types/d3-array/-/d3-array-3.0.1.tgz",
    "narHash": "sha256-EWG++B0YU5UlkmZwCk20v8KmCYfnGJ4+N0HGYxrEW00="
  },
  "3.0.2": {
    "type": "tarball",
    "url": "https://registry.npmjs.org/@types/d3-array/-/d3-array-3.0.2.tgz",
    "narHash": "sha256-i8iI8zvmglK/lNlZ4Q81p1zJGO6HdXX4cKKF6yKQzfM="
  },
  "3.0.3": {
    "type": "tarball",
    "url": "https://registry.npmjs.org/@types/d3-array/-/d3-array-3.0.3.tgz",
    "narHash": "sha256-epl3dDzyiUSnkN26CSd/eMbKZLJ8/ADSdv44O0MY1Y4="
  }
}
