{"trees":[{"from":{"id":"cfb-latest","type":"indirect"},"to":{"id":"cfb-1_2_2","type":"indirect"}},{"from":{"id":"cfb-0_10_0","type":"indirect"},"to":{"type":"tarball","url":"https://registry.npmjs.org/cfb/-/cfb-0.10.0.tgz"}},{"from":{"id":"cfb-0_10_1","type":"indirect"},"to":{"type":"tarball","url":"https://registry.npmjs.org/cfb/-/cfb-0.10.1.tgz"}},{"from":{"id":"cfb-0_10_2","type":"indirect"},"to":{"type":"tarball","url":"https://registry.npmjs.org/cfb/-/cfb-0.10.2.tgz"}},{"from":{"id":"cfb-0_10_2-a","type":"indirect"},"to":{"type":"tarball","url":"https://registry.npmjs.org/cfb/-/cfb-0.10.2-a.tgz"}},{"from":{"id":"cfb-0_10_3","type":"indirect"},"to":{"type":"tarball","url":"https://registry.npmjs.org/cfb/-/cfb-0.10.3.tgz"}},{"from":{"id":"cfb-0_10_3-a","type":"indirect"},"to":{"type":"tarball","url":"https://registry.npmjs.org/cfb/-/cfb-0.10.3-a.tgz"}},{"from":{"id":"cfb-0_11_0","type":"indirect"},"to":{"type":"tarball","url":"https://registry.npmjs.org/cfb/-/cfb-0.11.0.tgz"}},{"from":{"id":"cfb-0_11_1","type":"indirect"},"to":{"type":"tarball","url":"https://registry.npmjs.org/cfb/-/cfb-0.11.1.tgz"}},{"from":{"id":"cfb-0_12_0","type":"indirect"},"to":{"type":"tarball","url":"https://registry.npmjs.org/cfb/-/cfb-0.12.0.tgz"}},{"from":{"id":"cfb-0_12_1","type":"indirect"},"to":{"type":"tarball","url":"https://registry.npmjs.org/cfb/-/cfb-0.12.1.tgz"}},{"from":{"id":"cfb-0_13_0","type":"indirect"},"to":{"type":"tarball","url":"https://registry.npmjs.org/cfb/-/cfb-0.13.0.tgz"}},{"from":{"id":"cfb-0_13_1","type":"indirect"},"to":{"type":"tarball","url":"https://registry.npmjs.org/cfb/-/cfb-0.13.1.tgz"}},{"from":{"id":"cfb-0_13_2","type":"indirect"},"to":{"type":"tarball","url":"https://registry.npmjs.org/cfb/-/cfb-0.13.2.tgz"}},{"from":{"id":"cfb-0_8_1","type":"indirect"},"to":{"type":"tarball","url":"https://registry.npmjs.org/cfb/-/cfb-0.8.1.tgz"}},{"from":{"id":"cfb-0_9_1","type":"indirect"},"to":{"type":"tarball","url":"https://registry.npmjs.org/cfb/-/cfb-0.9.1.tgz"}},{"from":{"id":"cfb-1_0_0","type":"indirect"},"to":{"type":"tarball","url":"https://registry.npmjs.org/cfb/-/cfb-1.0.0.tgz"}},{"from":{"id":"cfb-1_0_1","type":"indirect"},"to":{"type":"tarball","url":"https://registry.npmjs.org/cfb/-/cfb-1.0.1.tgz"}},{"from":{"id":"cfb-1_0_2","type":"indirect"},"to":{"type":"tarball","url":"https://registry.npmjs.org/cfb/-/cfb-1.0.2.tgz"}},{"from":{"id":"cfb-1_0_3","type":"indirect"},"to":{"type":"tarball","url":"https://registry.npmjs.org/cfb/-/cfb-1.0.3.tgz"}},{"from":{"id":"cfb-1_0_4","type":"indirect"},"to":{"type":"tarball","url":"https://registry.npmjs.org/cfb/-/cfb-1.0.4.tgz"}},{"from":{"id":"cfb-1_0_5","type":"indirect"},"to":{"type":"tarball","url":"https://registry.npmjs.org/cfb/-/cfb-1.0.5.tgz"}},{"from":{"id":"cfb-1_0_6","type":"indirect"},"to":{"type":"tarball","url":"https://registry.npmjs.org/cfb/-/cfb-1.0.6.tgz"}},{"from":{"id":"cfb-1_0_7","type":"indirect"},"to":{"type":"tarball","url":"https://registry.npmjs.org/cfb/-/cfb-1.0.7.tgz"}},{"from":{"id":"cfb-1_0_8","type":"indirect"},"to":{"type":"tarball","url":"https://registry.npmjs.org/cfb/-/cfb-1.0.8.tgz"}},{"from":{"id":"cfb-1_1_0","type":"indirect"},"to":{"type":"tarball","url":"https://registry.npmjs.org/cfb/-/cfb-1.1.0.tgz"}},{"from":{"id":"cfb-1_1_1","type":"indirect"},"to":{"type":"tarball","url":"https://registry.npmjs.org/cfb/-/cfb-1.1.1.tgz"}},{"from":{"id":"cfb-1_1_2","type":"indirect"},"to":{"type":"tarball","url":"https://registry.npmjs.org/cfb/-/cfb-1.1.2.tgz"}},{"from":{"id":"cfb-1_1_3","type":"indirect"},"to":{"type":"tarball","url":"https://registry.npmjs.org/cfb/-/cfb-1.1.3.tgz"}},{"from":{"id":"cfb-1_1_4","type":"indirect"},"to":{"type":"tarball","url":"https://registry.npmjs.org/cfb/-/cfb-1.1.4.tgz"}},{"from":{"id":"cfb-1_2_0","type":"indirect"},"to":{"type":"tarball","url":"https://registry.npmjs.org/cfb/-/cfb-1.2.0.tgz"}},{"from":{"id":"cfb-1_2_1","type":"indirect"},"to":{"type":"tarball","url":"https://registry.npmjs.org/cfb/-/cfb-1.2.1.tgz"}},{"from":{"id":"cfb-1_2_2","type":"indirect"},"to":{"type":"tarball","url":"https://registry.npmjs.org/cfb/-/cfb-1.2.2.tgz"}}],"treelockVersion":1}