{"flakes":[{"from":{"id":"requires-port-latest","type":"indirect"},"to":{"id":"requires-port-1_0_0","type":"indirect"}},{"from":{"id":"requires-port-0_0_0","type":"indirect"},"to":{"type":"tarball","url":"https://registry.npmjs.org/requires-port/-/requires-port-0.0.0.tgz"}},{"from":{"id":"requires-port-0_0_1","type":"indirect"},"to":{"type":"tarball","url":"https://registry.npmjs.org/requires-port/-/requires-port-0.0.1.tgz"}},{"from":{"id":"requires-port-1_0_0","type":"indirect"},"to":{"type":"tarball","url":"https://registry.npmjs.org/requires-port/-/requires-port-1.0.0.tgz"}}],"version":2}