{"info":{"lastModifiedDate":"20221028151904","rev":"399-b27e650a40ce3401848efc664ab8db48"},"treelockVersion":1,"trees":[{"fetchInfo":{"narHash":"sha256-LCmyS8steckACJmMrZt0/eKwocs0te8RJukpYvNrYpc="},"from":{"id":"vue-loader--latest","type":"indirect"},"to":{"type":"tarball","url":"https://registry.npmjs.org/vue-loader/-/vue-loader-17.0.0.tgz"}},{"fetchInfo":{"narHash":"sha256-ViM8+SQh9BC9QdJK1xFBgGZ5aVruAWaCLVJlCPUXYXw="},"from":{"id":"vue-loader--0_1_0","type":"indirect"},"to":{"type":"tarball","url":"https://registry.npmjs.org/vue-loader/-/vue-loader-0.1.0.tgz"}},{"fetchInfo":{"narHash":"sha256-Bimg2AqaeSXpagz18kBpxZyJA74grkIU912pCo2PWx8="},"from":{"id":"vue-loader--0_2_0","type":"indirect"},"to":{"type":"tarball","url":"https://registry.npmjs.org/vue-loader/-/vue-loader-0.2.0.tgz"}},{"fetchInfo":{"narHash":"sha256-trJ/aQ/+39XuuFKdTjAuCGnXBjBmUP+zpWvqcjSBQlM="},"from":{"id":"vue-loader--0_3_0","type":"indirect"},"to":{"type":"tarball","url":"https://registry.npmjs.org/vue-loader/-/vue-loader-0.3.0.tgz"}},{"fetchInfo":{"narHash":"sha256-Ni8MSE+ug8rtT+UzXviJwzpQXsjUzfkQPCUL6JwjhQU="},"from":{"id":"vue-loader--1_1_0","type":"indirect"},"to":{"type":"tarball","url":"https://registry.npmjs.org/vue-loader/-/vue-loader-1.1.0.tgz"}},{"fetchInfo":{"narHash":"sha256-p3egP8UJvbptNxjMmSqqJdgMj8AVsvPI3E7i1LJc+Yc="},"from":{"id":"vue-loader--1_1_2","type":"indirect"},"to":{"type":"tarball","url":"https://registry.npmjs.org/vue-loader/-/vue-loader-1.1.2.tgz"}},{"fetchInfo":{"narHash":"sha256-k+KGKgZzOE17aEchqrj38Cv/sSUu/haf9rFmQIZxM/g="},"from":{"id":"vue-loader--1_1_3","type":"indirect"},"to":{"type":"tarball","url":"https://registry.npmjs.org/vue-loader/-/vue-loader-1.1.3.tgz"}},{"fetchInfo":{"narHash":"sha256-L/VNbLYO+FUze3CFZJMxh1TkCa4CCqx4OAUn0zIioMo="},"from":{"id":"vue-loader--1_1_4","type":"indirect"},"to":{"type":"tarball","url":"https://registry.npmjs.org/vue-loader/-/vue-loader-1.1.4.tgz"}},{"fetchInfo":{"narHash":"sha256-/sJdl0upKL9pWdgnszyRYpxG+aFOzuBpdQT82f67434="},"from":{"id":"vue-loader--1_1_5","type":"indirect"},"to":{"type":"tarball","url":"https://registry.npmjs.org/vue-loader/-/vue-loader-1.1.5.tgz"}},{"fetchInfo":{"narHash":"sha256-1oAYcLaHYkpyG0v1NxYGMk+YKJtT7Gi3amBZUTFe2rA="},"from":{"id":"vue-loader--1_1_6","type":"indirect"},"to":{"type":"tarball","url":"https://registry.npmjs.org/vue-loader/-/vue-loader-1.1.6.tgz"}},{"fetchInfo":{"narHash":"sha256-RI8Skcpz2WaBxzsJKhcah1N19oa6gA4RaxgCfYIKSx8="},"from":{"id":"vue-loader--10_0_0","type":"indirect"},"to":{"type":"tarball","url":"https://registry.npmjs.org/vue-loader/-/vue-loader-10.0.0.tgz"}},{"fetchInfo":{"narHash":"sha256-4V2XRXDKga14+6ckxCr3oNaZHsutvwhFlOOl3lx12F0="},"from":{"id":"vue-loader--10_0_1","type":"indirect"},"to":{"type":"tarball","url":"https://registry.npmjs.org/vue-loader/-/vue-loader-10.0.1.tgz"}},{"fetchInfo":{"narHash":"sha256-CHwg0kzNZKR7AuTLEcd27JnAl0UQ70W0TCecYF/eKvU="},"from":{"id":"vue-loader--10_0_2","type":"indirect"},"to":{"type":"tarball","url":"https://registry.npmjs.org/vue-loader/-/vue-loader-10.0.2.tgz"}},{"fetchInfo":{"narHash":"sha256-3mvnj0eW7oWF+2HuX/JjLBg5WGM28nmzbbeGdbe60C4="},"from":{"id":"vue-loader--10_0_3","type":"indirect"},"to":{"type":"tarball","url":"https://registry.npmjs.org/vue-loader/-/vue-loader-10.0.3.tgz"}},{"fetchInfo":{"narHash":"sha256-zZ7JJ3DoJvLVBQDHCUqOKaKa08WAVwk9t4i0t6Gcc3c="},"from":{"id":"vue-loader--10_0_4","type":"indirect"},"to":{"type":"tarball","url":"https://registry.npmjs.org/vue-loader/-/vue-loader-10.0.4.tgz"}},{"fetchInfo":{"narHash":"sha256-HPgoo0/v7dDVVvZC0jRVDI33QLlTjjq0YXHQqYip2iM="},"from":{"id":"vue-loader--10_1_0","type":"indirect"},"to":{"type":"tarball","url":"https://registry.npmjs.org/vue-loader/-/vue-loader-10.1.0.tgz"}},{"fetchInfo":{"narHash":"sha256-fcF/4QX0QUY5BUqIjfNoGHc9Y8LlROaQNQm7fuuFyW0="},"from":{"id":"vue-loader--10_1_1","type":"indirect"},"to":{"type":"tarball","url":"https://registry.npmjs.org/vue-loader/-/vue-loader-10.1.1.tgz"}},{"fetchInfo":{"narHash":"sha256-NRMc4kEUyX8qQAviCmRSB1JwQRNp3eJ9ceGtqhRByTo="},"from":{"id":"vue-loader--10_1_2","type":"indirect"},"to":{"type":"tarball","url":"https://registry.npmjs.org/vue-loader/-/vue-loader-10.1.2.tgz"}},{"fetchInfo":{"narHash":"sha256-ZZLVT9sIlaqBZRangRFj/KCTYIP8gFklGTgST7NU+fA="},"from":{"id":"vue-loader--10_2_0","type":"indirect"},"to":{"type":"tarball","url":"https://registry.npmjs.org/vue-loader/-/vue-loader-10.2.0.tgz"}},{"fetchInfo":{"narHash":"sha256-K9xTbEfCJq+B6WRQMkCTandcemA7jii7Mg/zjNev7hI="},"from":{"id":"vue-loader--10_2_1","type":"indirect"},"to":{"type":"tarball","url":"https://registry.npmjs.org/vue-loader/-/vue-loader-10.2.1.tgz"}},{"fetchInfo":{"narHash":"sha256-Do8cUnMvBTQTXGDmIoT6XBU0RsXkWX/YPOyhnVF0hEY="},"from":{"id":"vue-loader--10_2_2","type":"indirect"},"to":{"type":"tarball","url":"https://registry.npmjs.org/vue-loader/-/vue-loader-10.2.2.tgz"}},{"fetchInfo":{"narHash":"sha256-NwBSR6/wq017qUU4jFHtzp3DdZUCN4tbnsLMCQAFMcA="},"from":{"id":"vue-loader--10_2_3","type":"indirect"},"to":{"type":"tarball","url":"https://registry.npmjs.org/vue-loader/-/vue-loader-10.2.3.tgz"}},{"fetchInfo":{"narHash":"sha256-/lqyJSecEhWEBp/qGY+FcHctcHtIEIs6O6lOYpWugV4="},"from":{"id":"vue-loader--10_2_4","type":"indirect"},"to":{"type":"tarball","url":"https://registry.npmjs.org/vue-loader/-/vue-loader-10.2.4.tgz"}},{"fetchInfo":{"narHash":"sha256-fZjDRbXoG48+yFhbPGlKeEg84OB97KHehv2T0ullTTw="},"from":{"id":"vue-loader--10_3_0","type":"indirect"},"to":{"type":"tarball","url":"https://registry.npmjs.org/vue-loader/-/vue-loader-10.3.0.tgz"}},{"fetchInfo":{"narHash":"sha256-1FjxIECFT5eaTJiyht2kwc+cIpv4PKWeR+Rd78HOGWA="},"from":{"id":"vue-loader--11_0_0","type":"indirect"},"to":{"type":"tarball","url":"https://registry.npmjs.org/vue-loader/-/vue-loader-11.0.0.tgz"}},{"fetchInfo":{"narHash":"sha256-6nxiMvHTgVgc7bBF9pz8KkzXTarnyghk4VG91DsCCnY="},"from":{"id":"vue-loader--11_1_0","type":"indirect"},"to":{"type":"tarball","url":"https://registry.npmjs.org/vue-loader/-/vue-loader-11.1.0.tgz"}},{"fetchInfo":{"narHash":"sha256-bh4csk6WJ9T6yck/IzqM7byVEkv7MlemiaC4YXMCcI8="},"from":{"id":"vue-loader--11_1_1","type":"indirect"},"to":{"type":"tarball","url":"https://registry.npmjs.org/vue-loader/-/vue-loader-11.1.1.tgz"}},{"fetchInfo":{"narHash":"sha256-cYURrQcaM7XVTJTcctLm5ekE4NYMBhcZh8GYYgmAzM0="},"from":{"id":"vue-loader--11_1_2","type":"indirect"},"to":{"type":"tarball","url":"https://registry.npmjs.org/vue-loader/-/vue-loader-11.1.2.tgz"}},{"fetchInfo":{"narHash":"sha256-xCI5rmeDWac7BXgpYhxqmn835k3OkyMkf7CCFfCjA1o="},"from":{"id":"vue-loader--11_1_3","type":"indirect"},"to":{"type":"tarball","url":"https://registry.npmjs.org/vue-loader/-/vue-loader-11.1.3.tgz"}},{"fetchInfo":{"narHash":"sha256-HayHAH0J485YmzthXRcRLJc7de9Mn2mXIGbyQzHf4ic="},"from":{"id":"vue-loader--11_1_4","type":"indirect"},"to":{"type":"tarball","url":"https://registry.npmjs.org/vue-loader/-/vue-loader-11.1.4.tgz"}},{"fetchInfo":{"narHash":"sha256-n59TuiIRnkofPTisP4gwycCuEOYJUgGLlXZE9wKzAAg="},"from":{"id":"vue-loader--11_2_0","type":"indirect"},"to":{"type":"tarball","url":"https://registry.npmjs.org/vue-loader/-/vue-loader-11.2.0.tgz"}},{"fetchInfo":{"narHash":"sha256-9Zn+yM6QbffgLekBv2oocGDQv1JigZ3+Q8BRf64RzGA="},"from":{"id":"vue-loader--11_3_0","type":"indirect"},"to":{"type":"tarball","url":"https://registry.npmjs.org/vue-loader/-/vue-loader-11.3.0.tgz"}},{"fetchInfo":{"narHash":"sha256-UZmpdom8OZT9aPlAS2X8+g6wFMXkr679hWaFv6Lo/Ik="},"from":{"id":"vue-loader--11_3_1","type":"indirect"},"to":{"type":"tarball","url":"https://registry.npmjs.org/vue-loader/-/vue-loader-11.3.1.tgz"}},{"fetchInfo":{"narHash":"sha256-4tiMoDODaisMGj160qaLuW2IuibqqcSX7BGF7ssJHtQ="},"from":{"id":"vue-loader--11_3_2","type":"indirect"},"to":{"type":"tarball","url":"https://registry.npmjs.org/vue-loader/-/vue-loader-11.3.2.tgz"}},{"fetchInfo":{"narHash":"sha256-QoqubYXtKAUCTE2tnOl6h6AovOXqu7fVxs3Sx3H+V6w="},"from":{"id":"vue-loader--11_3_3","type":"indirect"},"to":{"type":"tarball","url":"https://registry.npmjs.org/vue-loader/-/vue-loader-11.3.3.tgz"}},{"fetchInfo":{"narHash":"sha256-rNXSPA9cYdhCR8V/fEWlYMczBgDuiUlbtP/jHur+LyE="},"from":{"id":"vue-loader--11_3_4","type":"indirect"},"to":{"type":"tarball","url":"https://registry.npmjs.org/vue-loader/-/vue-loader-11.3.4.tgz"}},{"fetchInfo":{"narHash":"sha256-CwEWT/Ign9HUzlfoKdKOv06pPUU2hS66ge2sf97ViUE="},"from":{"id":"vue-loader--12_0_0","type":"indirect"},"to":{"type":"tarball","url":"https://registry.npmjs.org/vue-loader/-/vue-loader-12.0.0.tgz"}},{"fetchInfo":{"narHash":"sha256-4vjDyh4iZYE0/BD3WU+rJNluRzA9gpCMgRD3rSyB1Bo="},"from":{"id":"vue-loader--12_0_1","type":"indirect"},"to":{"type":"tarball","url":"https://registry.npmjs.org/vue-loader/-/vue-loader-12.0.1.tgz"}},{"fetchInfo":{"narHash":"sha256-gPDuo3cwShQ/p289eVbZAYqMtRAJ2RzqRYqZHlR06MA="},"from":{"id":"vue-loader--12_0_2","type":"indirect"},"to":{"type":"tarball","url":"https://registry.npmjs.org/vue-loader/-/vue-loader-12.0.2.tgz"}},{"fetchInfo":{"narHash":"sha256-O/+1UyeTAw/WlaXiajEZxvOmbipNikXN6Jwt94Rurhc="},"from":{"id":"vue-loader--12_0_3","type":"indirect"},"to":{"type":"tarball","url":"https://registry.npmjs.org/vue-loader/-/vue-loader-12.0.3.tgz"}},{"fetchInfo":{"narHash":"sha256-G7s2D+tm+FXdWPc9Rcn2ikNVGyZQ1mDA6VyAIg40U1U="},"from":{"id":"vue-loader--12_0_4","type":"indirect"},"to":{"type":"tarball","url":"https://registry.npmjs.org/vue-loader/-/vue-loader-12.0.4.tgz"}},{"fetchInfo":{"narHash":"sha256-8ZUIUHMMyk/H3bgO7GEAaxWABoIl6jyHPDn3UfgC1AU="},"from":{"id":"vue-loader--12_1_0","type":"indirect"},"to":{"type":"tarball","url":"https://registry.npmjs.org/vue-loader/-/vue-loader-12.1.0.tgz"}},{"fetchInfo":{"narHash":"sha256-SzAOyyoujI72925bZtgvN6BKcBSVzytrhf89MM8BgC4="},"from":{"id":"vue-loader--12_1_1","type":"indirect"},"to":{"type":"tarball","url":"https://registry.npmjs.org/vue-loader/-/vue-loader-12.1.1.tgz"}},{"fetchInfo":{"narHash":"sha256-yXup/9HbDjM1IJHVxRd5nB5n1uzt96CxysFP1VoaP68="},"from":{"id":"vue-loader--12_2_0","type":"indirect"},"to":{"type":"tarball","url":"https://registry.npmjs.org/vue-loader/-/vue-loader-12.2.0.tgz"}},{"fetchInfo":{"narHash":"sha256-BaZIcLRYDnKTVPvJ5MJzKm3OUW9zY1+9DEJ3jwetr9c="},"from":{"id":"vue-loader--12_2_1","type":"indirect"},"to":{"type":"tarball","url":"https://registry.npmjs.org/vue-loader/-/vue-loader-12.2.1.tgz"}},{"fetchInfo":{"narHash":"sha256-yujVOmmua6534OEfYY8jrsfvzZqftFvj5dIoALCSrcU="},"from":{"id":"vue-loader--12_2_2","type":"indirect"},"to":{"type":"tarball","url":"https://registry.npmjs.org/vue-loader/-/vue-loader-12.2.2.tgz"}},{"fetchInfo":{"narHash":"sha256-xa7KuJaYqUUe9Mn7R+4d0B4Cdj+Mo5j14DSg/PdeWbE="},"from":{"id":"vue-loader--13_0_0","type":"indirect"},"to":{"type":"tarball","url":"https://registry.npmjs.org/vue-loader/-/vue-loader-13.0.0.tgz"}},{"fetchInfo":{"narHash":"sha256-T+3xbNmly8G7D3xr+QCsBbvhKNXTKlZl2YIfU9Bhcwo="},"from":{"id":"vue-loader--13_0_1","type":"indirect"},"to":{"type":"tarball","url":"https://registry.npmjs.org/vue-loader/-/vue-loader-13.0.1.tgz"}},{"fetchInfo":{"narHash":"sha256-l4pE8rBM0cMKeH4/EyafU4t4KPJhkrpENXdM6AOu7cg="},"from":{"id":"vue-loader--13_0_2","type":"indirect"},"to":{"type":"tarball","url":"https://registry.npmjs.org/vue-loader/-/vue-loader-13.0.2.tgz"}},{"fetchInfo":{"narHash":"sha256-eDoWWCbTHu6WRBtaZoxDcb1PNAgW6Qy5Sqn0ArdlFw0="},"from":{"id":"vue-loader--13_0_3","type":"indirect"},"to":{"type":"tarball","url":"https://registry.npmjs.org/vue-loader/-/vue-loader-13.0.3.tgz"}},{"fetchInfo":{"narHash":"sha256-Iulf15l4Cu4gHKtgDyqHbxFkzBw2mplIfGO6DaJYOyU="},"from":{"id":"vue-loader--13_0_4","type":"indirect"},"to":{"type":"tarball","url":"https://registry.npmjs.org/vue-loader/-/vue-loader-13.0.4.tgz"}},{"fetchInfo":{"narHash":"sha256-4i5n9I9k29+YvzQEH4Vrae31f0X+3Cn54uIRhMFug98="},"from":{"id":"vue-loader--13_0_5","type":"indirect"},"to":{"type":"tarball","url":"https://registry.npmjs.org/vue-loader/-/vue-loader-13.0.5.tgz"}},{"fetchInfo":{"narHash":"sha256-V71oXWFnaCfNNjdpWoFVx4meu5yIokMsuX7P+DsVayo="},"from":{"id":"vue-loader--13_1_0","type":"indirect"},"to":{"type":"tarball","url":"https://registry.npmjs.org/vue-loader/-/vue-loader-13.1.0.tgz"}},{"fetchInfo":{"narHash":"sha256-fvZhY/e8d8BSC+Q8LXOKkJ9AfODAOww5ncN7p4dxU3s="},"from":{"id":"vue-loader--13_2_0","type":"indirect"},"to":{"type":"tarball","url":"https://registry.npmjs.org/vue-loader/-/vue-loader-13.2.0.tgz"}},{"fetchInfo":{"narHash":"sha256-UbOghUwelAn2tILucSxD3UpPTGlVSppSSDaRrx/cK3o="},"from":{"id":"vue-loader--13_2_1","type":"indirect"},"to":{"type":"tarball","url":"https://registry.npmjs.org/vue-loader/-/vue-loader-13.2.1.tgz"}},{"fetchInfo":{"narHash":"sha256-O5bpug6coEkWbNBbDJ95dEAKENPoxkj74J+Uvod23jI="},"from":{"id":"vue-loader--13_3_0","type":"indirect"},"to":{"type":"tarball","url":"https://registry.npmjs.org/vue-loader/-/vue-loader-13.3.0.tgz"}},{"fetchInfo":{"narHash":"sha256-1ab5SWFhR2Yqf6ZFr8yLRQUFiN/vLKcwl9un4SJVpLQ="},"from":{"id":"vue-loader--13_4_0","type":"indirect"},"to":{"type":"tarball","url":"https://registry.npmjs.org/vue-loader/-/vue-loader-13.4.0.tgz"}},{"fetchInfo":{"narHash":"sha256-SwW2SR2ho6itwtScAprLvnr3t0y/60Pcq25FBGZ6Kf4="},"from":{"id":"vue-loader--13_5_0","type":"indirect"},"to":{"type":"tarball","url":"https://registry.npmjs.org/vue-loader/-/vue-loader-13.5.0.tgz"}},{"fetchInfo":{"narHash":"sha256-0LK7GxF28iDids5c1M0/arg7cZBcRdrsNatv2wibEyg="},"from":{"id":"vue-loader--13_5_1","type":"indirect"},"to":{"type":"tarball","url":"https://registry.npmjs.org/vue-loader/-/vue-loader-13.5.1.tgz"}},{"fetchInfo":{"narHash":"sha256-XtePpaL/YT2f81bJf65yHVdrKG9tXLjsesSbJqO53Lo="},"from":{"id":"vue-loader--13_6_0","type":"indirect"},"to":{"type":"tarball","url":"https://registry.npmjs.org/vue-loader/-/vue-loader-13.6.0.tgz"}},{"fetchInfo":{"narHash":"sha256-h6x9D9OFX/y40bd7kvAPjZw+eM837EAUcJJVAzUnuao="},"from":{"id":"vue-loader--13_6_1","type":"indirect"},"to":{"type":"tarball","url":"https://registry.npmjs.org/vue-loader/-/vue-loader-13.6.1.tgz"}},{"fetchInfo":{"narHash":"sha256-0Cxlca06bJQMhh6kspEeuS7gWh40rRQHtRAirIoA/kI="},"from":{"id":"vue-loader--13_6_2","type":"indirect"},"to":{"type":"tarball","url":"https://registry.npmjs.org/vue-loader/-/vue-loader-13.6.2.tgz"}},{"fetchInfo":{"narHash":"sha256-UyDe8TNM8JoV7/Y5u1LzhTDNFXkI8NDY+4756VmWEJY="},"from":{"id":"vue-loader--13_7_0","type":"indirect"},"to":{"type":"tarball","url":"https://registry.npmjs.org/vue-loader/-/vue-loader-13.7.0.tgz"}},{"fetchInfo":{"narHash":"sha256-2kCY3EsQdyynlRdcUfwQg1pxhLJofyQorMw1+Fo4zho="},"from":{"id":"vue-loader--13_7_1","type":"indirect"},"to":{"type":"tarball","url":"https://registry.npmjs.org/vue-loader/-/vue-loader-13.7.1.tgz"}},{"fetchInfo":{"narHash":"sha256-pcqYES8cpJ9q5KAfB1iysIVY1eQdGgLi37pl+yOT8JQ="},"from":{"id":"vue-loader--13_7_2","type":"indirect"},"to":{"type":"tarball","url":"https://registry.npmjs.org/vue-loader/-/vue-loader-13.7.2.tgz"}},{"fetchInfo":{"narHash":"sha256-lv8tXugIiyfRGyzjKQFcczyAnise6c5aO2NQai+Dls4="},"from":{"id":"vue-loader--13_7_3","type":"indirect"},"to":{"type":"tarball","url":"https://registry.npmjs.org/vue-loader/-/vue-loader-13.7.3.tgz"}},{"fetchInfo":{"narHash":"sha256-Xsf/MX5N4JysJvD/nojrIL9slsHJunUgD4FOKZ3ESvk="},"from":{"id":"vue-loader--14_0_0","type":"indirect"},"to":{"type":"tarball","url":"https://registry.npmjs.org/vue-loader/-/vue-loader-14.0.0.tgz"}},{"fetchInfo":{"narHash":"sha256-R2QzHbBBH7XmdSzr6PV++SYAmUIeMsBk49Ujj7Bc/wM="},"from":{"id":"vue-loader--14_0_1","type":"indirect"},"to":{"type":"tarball","url":"https://registry.npmjs.org/vue-loader/-/vue-loader-14.0.1.tgz"}},{"fetchInfo":{"narHash":"sha256-YSZvE3xsMXcCctA8tZRvLdRkIiRzS3Egsdo8KN2eYsw="},"from":{"id":"vue-loader--14_0_2","type":"indirect"},"to":{"type":"tarball","url":"https://registry.npmjs.org/vue-loader/-/vue-loader-14.0.2.tgz"}},{"fetchInfo":{"narHash":"sha256-NY7JfiJlYYOIxFi9R2ol85u/2kqbbedN+EC22SD+z20="},"from":{"id":"vue-loader--14_0_3","type":"indirect"},"to":{"type":"tarball","url":"https://registry.npmjs.org/vue-loader/-/vue-loader-14.0.3.tgz"}},{"fetchInfo":{"narHash":"sha256-KUbt6L6yaKmE7iVN3Jusy1AalkNH2baMU52QQkp3/Is="},"from":{"id":"vue-loader--14_1_0","type":"indirect"},"to":{"type":"tarball","url":"https://registry.npmjs.org/vue-loader/-/vue-loader-14.1.0.tgz"}},{"fetchInfo":{"narHash":"sha256-gf4Y97KeUlazAShqIAigjxHeX120I92+rvADv/bTGzg="},"from":{"id":"vue-loader--14_1_1","type":"indirect"},"to":{"type":"tarball","url":"https://registry.npmjs.org/vue-loader/-/vue-loader-14.1.1.tgz"}},{"fetchInfo":{"narHash":"sha256-Dn/7Q2WqGa18i5BIQD31FMp/eRMb642tRuO/Yj9f4ms="},"from":{"id":"vue-loader--14_2_0","type":"indirect"},"to":{"type":"tarball","url":"https://registry.npmjs.org/vue-loader/-/vue-loader-14.2.0.tgz"}},{"fetchInfo":{"narHash":"sha256-D0MMimuZeWTDb1B3zE0YHhQ8vPNd3THFiq8yc7yhTFg="},"from":{"id":"vue-loader--14_2_1","type":"indirect"},"to":{"type":"tarball","url":"https://registry.npmjs.org/vue-loader/-/vue-loader-14.2.1.tgz"}},{"fetchInfo":{"narHash":"sha256-H0clzV36N9sjwHvCkuOB6jmomWN1Kjth5hvzP83D1fk="},"from":{"id":"vue-loader--14_2_2","type":"indirect"},"to":{"type":"tarball","url":"https://registry.npmjs.org/vue-loader/-/vue-loader-14.2.2.tgz"}},{"fetchInfo":{"narHash":"sha256-i9N0sSREKhd1maA1ygbyAoYyxyp8q6Zh2NLEBx+z8AQ="},"from":{"id":"vue-loader--14_2_3","type":"indirect"},"to":{"type":"tarball","url":"https://registry.npmjs.org/vue-loader/-/vue-loader-14.2.3.tgz"}},{"fetchInfo":{"narHash":"sha256-v5A7NqtqcK5Fr47wn+TXhQ1Bgck6CCuwlLVpCjZgs0E="},"from":{"id":"vue-loader--14_2_4","type":"indirect"},"to":{"type":"tarball","url":"https://registry.npmjs.org/vue-loader/-/vue-loader-14.2.4.tgz"}},{"fetchInfo":{"narHash":"sha256-XMKxAVQJ1jINYaXahYsZZH6gueZoe+YoLX+KuKPym+A="},"from":{"id":"vue-loader--15_0_0","type":"indirect"},"to":{"type":"tarball","url":"https://registry.npmjs.org/vue-loader/-/vue-loader-15.0.0.tgz"}},{"fetchInfo":{"narHash":"sha256-WXkhMt/LBjOQkdyx6gNLFoMFb9jx7uPRGJgbi6LkJvo="},"from":{"id":"vue-loader--15_0_1","type":"indirect"},"to":{"type":"tarball","url":"https://registry.npmjs.org/vue-loader/-/vue-loader-15.0.1.tgz"}},{"fetchInfo":{"narHash":"sha256-Aom7fjReTM3um5kR4+112Zfc2de3jAOr2hUyN9Zo+6M="},"from":{"id":"vue-loader--15_0_10","type":"indirect"},"to":{"type":"tarball","url":"https://registry.npmjs.org/vue-loader/-/vue-loader-15.0.10.tgz"}},{"fetchInfo":{"narHash":"sha256-2jWaitZDsX07dYLiQL9KeQykIjdYpkLPCRi98sDZvHs="},"from":{"id":"vue-loader--15_0_11","type":"indirect"},"to":{"type":"tarball","url":"https://registry.npmjs.org/vue-loader/-/vue-loader-15.0.11.tgz"}},{"fetchInfo":{"narHash":"sha256-QlDTRqMfdr29pNEU1vB7qgXzhd6k9o94L+vYAiSUaB8="},"from":{"id":"vue-loader--15_0_12","type":"indirect"},"to":{"type":"tarball","url":"https://registry.npmjs.org/vue-loader/-/vue-loader-15.0.12.tgz"}},{"fetchInfo":{"narHash":"sha256-T2Whe/F+fly638AOw2ROblyJfVm0wyp33HHGNMz+CRA="},"from":{"id":"vue-loader--15_0_2","type":"indirect"},"to":{"type":"tarball","url":"https://registry.npmjs.org/vue-loader/-/vue-loader-15.0.2.tgz"}},{"fetchInfo":{"narHash":"sha256-/R6jZxjvXFr003jFH/UTzFo8Lg97kBY2dp6HckUECuA="},"from":{"id":"vue-loader--15_0_3","type":"indirect"},"to":{"type":"tarball","url":"https://registry.npmjs.org/vue-loader/-/vue-loader-15.0.3.tgz"}},{"fetchInfo":{"narHash":"sha256-pLf45EaD/rLM6f27Dwtey8aIB/b+Y+U9knl95F0J/64="},"from":{"id":"vue-loader--15_0_4","type":"indirect"},"to":{"type":"tarball","url":"https://registry.npmjs.org/vue-loader/-/vue-loader-15.0.4.tgz"}},{"fetchInfo":{"narHash":"sha256-S6ljHN0dASYsxoiXMjvA6eKdUzTP5pQUlLye9uL6rs0="},"from":{"id":"vue-loader--15_0_5","type":"indirect"},"to":{"type":"tarball","url":"https://registry.npmjs.org/vue-loader/-/vue-loader-15.0.5.tgz"}},{"fetchInfo":{"narHash":"sha256-vLaZSobW1e9sW8EbaY8R68qlQd5XqfkZyFqmmHSahQo="},"from":{"id":"vue-loader--15_0_6","type":"indirect"},"to":{"type":"tarball","url":"https://registry.npmjs.org/vue-loader/-/vue-loader-15.0.6.tgz"}},{"fetchInfo":{"narHash":"sha256-PIsclbNg8ylyRuRF06t4GFcsIQ9oaoRokhhLPG29rkg="},"from":{"id":"vue-loader--15_0_7","type":"indirect"},"to":{"type":"tarball","url":"https://registry.npmjs.org/vue-loader/-/vue-loader-15.0.7.tgz"}},{"fetchInfo":{"narHash":"sha256-AEVlLRHQ3DSFMezTW4WCcdGHhyOMRfiQ3WvOINMIquY="},"from":{"id":"vue-loader--15_0_8","type":"indirect"},"to":{"type":"tarball","url":"https://registry.npmjs.org/vue-loader/-/vue-loader-15.0.8.tgz"}},{"fetchInfo":{"narHash":"sha256-nR7wA9+EomDTxGVfXdHU+usijOdoeD5gdNk8iqhwQJ4="},"from":{"id":"vue-loader--15_0_9","type":"indirect"},"to":{"type":"tarball","url":"https://registry.npmjs.org/vue-loader/-/vue-loader-15.0.9.tgz"}},{"fetchInfo":{"narHash":"sha256-9C5aapHr/SJODgJdfyO6UO7pnU6PnhEhnhi+cpJiQyY="},"from":{"id":"vue-loader--15_1_0","type":"indirect"},"to":{"type":"tarball","url":"https://registry.npmjs.org/vue-loader/-/vue-loader-15.1.0.tgz"}},{"fetchInfo":{"narHash":"sha256-SqQL5CyBThYB+ZJuudFKy3/uR+BOse7QcOc36HymAWQ="},"from":{"id":"vue-loader--15_10_0","type":"indirect"},"to":{"type":"tarball","url":"https://registry.npmjs.org/vue-loader/-/vue-loader-15.10.0.tgz"}},{"fetchInfo":{"narHash":"sha256-jWBXUpl64g3cMKpLadbgAhxrrdNTxGgg4+IQ1ab6OQ0="},"from":{"id":"vue-loader--15_2_0","type":"indirect"},"to":{"type":"tarball","url":"https://registry.npmjs.org/vue-loader/-/vue-loader-15.2.0.tgz"}},{"fetchInfo":{"narHash":"sha256-A5a4Y6G175uvKXtYozEiRWz1/Qh6nnJnnEYNLegY7nU="},"from":{"id":"vue-loader--15_2_1","type":"indirect"},"to":{"type":"tarball","url":"https://registry.npmjs.org/vue-loader/-/vue-loader-15.2.1.tgz"}},{"fetchInfo":{"narHash":"sha256-1EH1o+Ue2GQca8/mYL1ah+orDLm57/tVB8JswCxjRwM="},"from":{"id":"vue-loader--15_2_2","type":"indirect"},"to":{"type":"tarball","url":"https://registry.npmjs.org/vue-loader/-/vue-loader-15.2.2.tgz"}},{"fetchInfo":{"narHash":"sha256-hkyDTGqR7ALnxlw+nNLaOdi51FcAn8XLePWFzHgsxU4="},"from":{"id":"vue-loader--15_2_3","type":"indirect"},"to":{"type":"tarball","url":"https://registry.npmjs.org/vue-loader/-/vue-loader-15.2.3.tgz"}},{"fetchInfo":{"narHash":"sha256-F4s3gTmvYiSOSf+ermuah6jN1DZLQFAxIUgDsJCCLl0="},"from":{"id":"vue-loader--15_2_4","type":"indirect"},"to":{"type":"tarball","url":"https://registry.npmjs.org/vue-loader/-/vue-loader-15.2.4.tgz"}},{"fetchInfo":{"narHash":"sha256-kAVO/5nW+JD16YrLhLrSOy8dfEOAn6cqunvfw6fjwYY="},"from":{"id":"vue-loader--15_2_5","type":"indirect"},"to":{"type":"tarball","url":"https://registry.npmjs.org/vue-loader/-/vue-loader-15.2.5.tgz"}},{"fetchInfo":{"narHash":"sha256-fODF/5jdhS0FAoOTL6Srwa1bq0A09qGhlOpR9vh75wI="},"from":{"id":"vue-loader--15_2_6","type":"indirect"},"to":{"type":"tarball","url":"https://registry.npmjs.org/vue-loader/-/vue-loader-15.2.6.tgz"}},{"fetchInfo":{"narHash":"sha256-zOCSuwHAKwJ0yfYdspmh8yzBNiNDFuGXvnRV1Cit2r4="},"from":{"id":"vue-loader--15_2_7","type":"indirect"},"to":{"type":"tarball","url":"https://registry.npmjs.org/vue-loader/-/vue-loader-15.2.7.tgz"}},{"fetchInfo":{"narHash":"sha256-SPr60W1+y0Mm5c+FE9VEQmJXCWswyX1AGnzokza5feE="},"from":{"id":"vue-loader--15_3_0","type":"indirect"},"to":{"type":"tarball","url":"https://registry.npmjs.org/vue-loader/-/vue-loader-15.3.0.tgz"}},{"fetchInfo":{"narHash":"sha256-gGJ++UJSRCjoadiwvSbted/iIr+BZP9cxNK4DvJEvJ0="},"from":{"id":"vue-loader--15_4_0","type":"indirect"},"to":{"type":"tarball","url":"https://registry.npmjs.org/vue-loader/-/vue-loader-15.4.0.tgz"}},{"fetchInfo":{"narHash":"sha256-AfT5mCAUAJ++0HoQy+cHgcE4BWGR9nUjbJhKQhkrE9s="},"from":{"id":"vue-loader--15_4_1","type":"indirect"},"to":{"type":"tarball","url":"https://registry.npmjs.org/vue-loader/-/vue-loader-15.4.1.tgz"}},{"fetchInfo":{"narHash":"sha256-1Deno4mj2g/ZN4Hv2BeTWV7dNYhmhmwKwEiAk15bYP8="},"from":{"id":"vue-loader--15_4_2","type":"indirect"},"to":{"type":"tarball","url":"https://registry.npmjs.org/vue-loader/-/vue-loader-15.4.2.tgz"}},{"fetchInfo":{"narHash":"sha256-V4cE5IwbvRWcW8DUyNm+nU+HVfw76GVBsfFlGgHpBJg="},"from":{"id":"vue-loader--15_5_0","type":"indirect"},"to":{"type":"tarball","url":"https://registry.npmjs.org/vue-loader/-/vue-loader-15.5.0.tgz"}},{"fetchInfo":{"narHash":"sha256-ssZtBsaKE9SWLOPSoctJ714sLKXIakYItosdDPo13jA="},"from":{"id":"vue-loader--15_5_1","type":"indirect"},"to":{"type":"tarball","url":"https://registry.npmjs.org/vue-loader/-/vue-loader-15.5.1.tgz"}},{"fetchInfo":{"narHash":"sha256-THQ2aTIXN7Y+T0LpD6ngL+xi9z1A/xlmV3+UDmI3NOo="},"from":{"id":"vue-loader--15_6_0","type":"indirect"},"to":{"type":"tarball","url":"https://registry.npmjs.org/vue-loader/-/vue-loader-15.6.0.tgz"}},{"fetchInfo":{"narHash":"sha256-KcxB+BDuezVjhrB+ae+xlGVJGdOsSNSgx+rUuEVHAak="},"from":{"id":"vue-loader--15_6_1","type":"indirect"},"to":{"type":"tarball","url":"https://registry.npmjs.org/vue-loader/-/vue-loader-15.6.1.tgz"}},{"fetchInfo":{"narHash":"sha256-tpjuyCR6y2aolHkr+FhDlM9QiwK2YEM9TD/zLpjN1Bc="},"from":{"id":"vue-loader--15_6_2","type":"indirect"},"to":{"type":"tarball","url":"https://registry.npmjs.org/vue-loader/-/vue-loader-15.6.2.tgz"}},{"fetchInfo":{"narHash":"sha256-e5/z5kJwGTV69ZnmKU6ikgGXSKA6XS8Ag6yw/qCtZu8="},"from":{"id":"vue-loader--15_6_3","type":"indirect"},"to":{"type":"tarball","url":"https://registry.npmjs.org/vue-loader/-/vue-loader-15.6.3.tgz"}},{"fetchInfo":{"narHash":"sha256-C60WwEoyEEStF6oQVjn7uxcTmNmzuhdezYfdMbHBGgs="},"from":{"id":"vue-loader--15_6_4","type":"indirect"},"to":{"type":"tarball","url":"https://registry.npmjs.org/vue-loader/-/vue-loader-15.6.4.tgz"}},{"fetchInfo":{"narHash":"sha256-c3JSlQddKUgtGJmXIXMQjc/Ew68DNIXuFO8FJG872nw="},"from":{"id":"vue-loader--15_7_0","type":"indirect"},"to":{"type":"tarball","url":"https://registry.npmjs.org/vue-loader/-/vue-loader-15.7.0.tgz"}},{"fetchInfo":{"narHash":"sha256-H6hfWFS+7y8mcMlGvQdmd9v80gv/ziE03O1J2dSGMRw="},"from":{"id":"vue-loader--15_7_1","type":"indirect"},"to":{"type":"tarball","url":"https://registry.npmjs.org/vue-loader/-/vue-loader-15.7.1.tgz"}},{"fetchInfo":{"narHash":"sha256-z8WxeSu9z41umq5lVFgnZ5WK00udlOmqDIOFueKsfzQ="},"from":{"id":"vue-loader--15_7_2","type":"indirect"},"to":{"type":"tarball","url":"https://registry.npmjs.org/vue-loader/-/vue-loader-15.7.2.tgz"}},{"fetchInfo":{"narHash":"sha256-/oEAiLo8n+9nmTt2QbSLu+zOizU2iTEcs/hvObzA9uk="},"from":{"id":"vue-loader--15_8_0","type":"indirect"},"to":{"type":"tarball","url":"https://registry.npmjs.org/vue-loader/-/vue-loader-15.8.0.tgz"}},{"fetchInfo":{"narHash":"sha256-fhTClTwrKJJXFEsnVBP8Pve+aPPm9PnwW4rGxmME+3o="},"from":{"id":"vue-loader--15_8_1","type":"indirect"},"to":{"type":"tarball","url":"https://registry.npmjs.org/vue-loader/-/vue-loader-15.8.1.tgz"}},{"fetchInfo":{"narHash":"sha256-3NCRfVAunD7QW0OeZIILIZlDKs6XNj9fq/qOAB4PW8E="},"from":{"id":"vue-loader--15_8_2","type":"indirect"},"to":{"type":"tarball","url":"https://registry.npmjs.org/vue-loader/-/vue-loader-15.8.2.tgz"}},{"fetchInfo":{"narHash":"sha256-7WuR9c5UYrIz8ujZ+WTJ78m8SJv8+RGGMPt6bolQ5pw="},"from":{"id":"vue-loader--15_8_3","type":"indirect"},"to":{"type":"tarball","url":"https://registry.npmjs.org/vue-loader/-/vue-loader-15.8.3.tgz"}},{"fetchInfo":{"narHash":"sha256-ncbI1xO591ax1eIL6ErKw0RVnOXr77NL/6GGhB8wmpA="},"from":{"id":"vue-loader--15_9_0","type":"indirect"},"to":{"type":"tarball","url":"https://registry.npmjs.org/vue-loader/-/vue-loader-15.9.0.tgz"}},{"fetchInfo":{"narHash":"sha256-1PcAKTVYfQT5UlFoA1CEVpRJbkjtK5Ae6VZYkF3Thx4="},"from":{"id":"vue-loader--15_9_1","type":"indirect"},"to":{"type":"tarball","url":"https://registry.npmjs.org/vue-loader/-/vue-loader-15.9.1.tgz"}},{"fetchInfo":{"narHash":"sha256-jX7ezr3yN1Vmg2McpuJ73GyCMgk86t8gAv0pNl8uICU="},"from":{"id":"vue-loader--15_9_2","type":"indirect"},"to":{"type":"tarball","url":"https://registry.npmjs.org/vue-loader/-/vue-loader-15.9.2.tgz"}},{"fetchInfo":{"narHash":"sha256-1d/XnbmaKxBsipDd4tNPoRgwIKVHhatAR4cuG2JFU+g="},"from":{"id":"vue-loader--15_9_3","type":"indirect"},"to":{"type":"tarball","url":"https://registry.npmjs.org/vue-loader/-/vue-loader-15.9.3.tgz"}},{"fetchInfo":{"narHash":"sha256-wSDp2x0f2X2E5J5QkdzYovMNRw2vfPM8c1Xz6Kqgz9Q="},"from":{"id":"vue-loader--15_9_4","type":"indirect"},"to":{"type":"tarball","url":"https://registry.npmjs.org/vue-loader/-/vue-loader-15.9.4.tgz"}},{"fetchInfo":{"narHash":"sha256-aARI43zhVM3evqH3xpVTG4t8fX1CYFg/ALwjQGCBZ0Y="},"from":{"id":"vue-loader--15_9_5","type":"indirect"},"to":{"type":"tarball","url":"https://registry.npmjs.org/vue-loader/-/vue-loader-15.9.5.tgz"}},{"fetchInfo":{"narHash":"sha256-uMrUN3D9kYqLZq6d2OQyZDhQkRHNVJbcj/9x2HCIWPo="},"from":{"id":"vue-loader--15_9_6","type":"indirect"},"to":{"type":"tarball","url":"https://registry.npmjs.org/vue-loader/-/vue-loader-15.9.6.tgz"}},{"fetchInfo":{"narHash":"sha256-R7mqBVS2G2HiWF0bTY0AH1EAFqFo4LK75nAXvT2FJbI="},"from":{"id":"vue-loader--15_9_7","type":"indirect"},"to":{"type":"tarball","url":"https://registry.npmjs.org/vue-loader/-/vue-loader-15.9.7.tgz"}},{"fetchInfo":{"narHash":"sha256-mcnqWI2pvrFiHCZ6p944YBp6R/g0nC2Wg5h+uI5ubYU="},"from":{"id":"vue-loader--15_9_8","type":"indirect"},"to":{"type":"tarball","url":"https://registry.npmjs.org/vue-loader/-/vue-loader-15.9.8.tgz"}},{"fetchInfo":{"narHash":"sha256-GHzoVR/mXhFZfYIxTr9RgqQLPfVqJAVuAxUp3E53CC0="},"from":{"id":"vue-loader--16_0_0","type":"indirect"},"to":{"type":"tarball","url":"https://registry.npmjs.org/vue-loader/-/vue-loader-16.0.0.tgz"}},{"fetchInfo":{"narHash":"sha256-VccqHtRf+eC/Lj79TiI3eicHXacEHShQmkZeRw+aGc8="},"from":{"id":"vue-loader--16_1_0","type":"indirect"},"to":{"type":"tarball","url":"https://registry.npmjs.org/vue-loader/-/vue-loader-16.1.0.tgz"}},{"fetchInfo":{"narHash":"sha256-JpCAWKFjR5S2QWKuRIaY3X71576awpqC6HSjyCqHhJs="},"from":{"id":"vue-loader--16_1_1","type":"indirect"},"to":{"type":"tarball","url":"https://registry.npmjs.org/vue-loader/-/vue-loader-16.1.1.tgz"}},{"fetchInfo":{"narHash":"sha256-iibwwoJL1WRIwIt5N3IXrLZBoEINgrFsqWyJ6mqylh8="},"from":{"id":"vue-loader--16_1_2","type":"indirect"},"to":{"type":"tarball","url":"https://registry.npmjs.org/vue-loader/-/vue-loader-16.1.2.tgz"}},{"fetchInfo":{"narHash":"sha256-b2w+kshGPQ7Gki0cLCeHrbbfgTITs0jeEq4CFJCN7ec="},"from":{"id":"vue-loader--16_2_0","type":"indirect"},"to":{"type":"tarball","url":"https://registry.npmjs.org/vue-loader/-/vue-loader-16.2.0.tgz"}},{"fetchInfo":{"narHash":"sha256-WwlLMDXRFxt6T07UNvrKVGdxrQ5LwuRtOLROXteSAOE="},"from":{"id":"vue-loader--16_3_0","type":"indirect"},"to":{"type":"tarball","url":"https://registry.npmjs.org/vue-loader/-/vue-loader-16.3.0.tgz"}},{"fetchInfo":{"narHash":"sha256-V5ALNcvzo+YyiLZ1I8UMVE807Dm/n1+a6hMg/hGtjiU="},"from":{"id":"vue-loader--16_3_1","type":"indirect"},"to":{"type":"tarball","url":"https://registry.npmjs.org/vue-loader/-/vue-loader-16.3.1.tgz"}},{"fetchInfo":{"narHash":"sha256-GT5ZgsYAuwOqsE50uJOZ1OWdCeBqcxIPi70SLAXBggc="},"from":{"id":"vue-loader--16_3_2","type":"indirect"},"to":{"type":"tarball","url":"https://registry.npmjs.org/vue-loader/-/vue-loader-16.3.2.tgz"}},{"fetchInfo":{"narHash":"sha256-HflW5h7HjY/Zfnxp6gQcM0k7lcEEY11vyWynBhudLdE="},"from":{"id":"vue-loader--16_3_3","type":"indirect"},"to":{"type":"tarball","url":"https://registry.npmjs.org/vue-loader/-/vue-loader-16.3.3.tgz"}},{"fetchInfo":{"narHash":"sha256-0Pmfz1QOEgTx1yu5HHTeQcYVQaeRZuX8v25/HnJOvn0="},"from":{"id":"vue-loader--16_4_0","type":"indirect"},"to":{"type":"tarball","url":"https://registry.npmjs.org/vue-loader/-/vue-loader-16.4.0.tgz"}},{"fetchInfo":{"narHash":"sha256-MKIv9e6X/Ssajn7D3pPTgFoXK9QtUEEF+Af532Wh4Cc="},"from":{"id":"vue-loader--16_4_1","type":"indirect"},"to":{"type":"tarball","url":"https://registry.npmjs.org/vue-loader/-/vue-loader-16.4.1.tgz"}},{"fetchInfo":{"narHash":"sha256-vyakRbzB2fX7aeAy+tn+b3Szo2f9wlrIOCXrylSIQA8="},"from":{"id":"vue-loader--16_5_0","type":"indirect"},"to":{"type":"tarball","url":"https://registry.npmjs.org/vue-loader/-/vue-loader-16.5.0.tgz"}},{"fetchInfo":{"narHash":"sha256-b9h/B8gkfrw8i9Swmb9ZXGELD9b685lC4rHPJn8FsjQ="},"from":{"id":"vue-loader--16_6_0","type":"indirect"},"to":{"type":"tarball","url":"https://registry.npmjs.org/vue-loader/-/vue-loader-16.6.0.tgz"}},{"fetchInfo":{"narHash":"sha256-elGPFoNtoOXKnFQZjPDMVwwAQ3V1TM9gF4zGkJGI0uI="},"from":{"id":"vue-loader--16_7_0","type":"indirect"},"to":{"type":"tarball","url":"https://registry.npmjs.org/vue-loader/-/vue-loader-16.7.0.tgz"}},{"fetchInfo":{"narHash":"sha256-oO6r4FH9mBhJKKeZpDyY1L+4UBhjQXWP67grbMTgf5I="},"from":{"id":"vue-loader--16_7_1","type":"indirect"},"to":{"type":"tarball","url":"https://registry.npmjs.org/vue-loader/-/vue-loader-16.7.1.tgz"}},{"fetchInfo":{"narHash":"sha256-fIeG9WeUIhcWiIeM0bk38ZKsg1nCGfpsbyWn5B2kJDU="},"from":{"id":"vue-loader--16_8_0","type":"indirect"},"to":{"type":"tarball","url":"https://registry.npmjs.org/vue-loader/-/vue-loader-16.8.0.tgz"}},{"fetchInfo":{"narHash":"sha256-mvMpYWiazMKyLkOiVOljcsI00oVRGYLA+lacfH9UKck="},"from":{"id":"vue-loader--16_8_1","type":"indirect"},"to":{"type":"tarball","url":"https://registry.npmjs.org/vue-loader/-/vue-loader-16.8.1.tgz"}},{"fetchInfo":{"narHash":"sha256-t+z59ITwQsMUkc+3GBI0z0w0vppcQT/G8XWJf8bInTo="},"from":{"id":"vue-loader--16_8_2","type":"indirect"},"to":{"type":"tarball","url":"https://registry.npmjs.org/vue-loader/-/vue-loader-16.8.2.tgz"}},{"fetchInfo":{"narHash":"sha256-H6QaEa6rt5my3h6w5Ef0HpDCTwOalc8vk7zeNET0yjU="},"from":{"id":"vue-loader--16_8_3","type":"indirect"},"to":{"type":"tarball","url":"https://registry.npmjs.org/vue-loader/-/vue-loader-16.8.3.tgz"}},{"fetchInfo":{"narHash":"sha256-LCmyS8steckACJmMrZt0/eKwocs0te8RJukpYvNrYpc="},"from":{"id":"vue-loader--17_0_0","type":"indirect"},"to":{"type":"tarball","url":"https://registry.npmjs.org/vue-loader/-/vue-loader-17.0.0.tgz"}},{"fetchInfo":{"narHash":"sha256-PLypvtQIE9GJcvArOeAPWGlR6qf/IfS6KuVQQmKldig="},"from":{"id":"vue-loader--17_0_1","type":"indirect"},"to":{"type":"tarball","url":"https://registry.npmjs.org/vue-loader/-/vue-loader-17.0.1.tgz"}},{"fetchInfo":{"narHash":"sha256-fb/rU7nuqgw/S+furRSE3/Id9NpBGKtJ3BvCebLtPHM="},"from":{"id":"vue-loader--2_0_0","type":"indirect"},"to":{"type":"tarball","url":"https://registry.npmjs.org/vue-loader/-/vue-loader-2.0.0.tgz"}},{"fetchInfo":{"narHash":"sha256-O7CeIcaldDXN9k6dV7lbVtGRrHg+Kv59kRbUO3z9Qv8="},"from":{"id":"vue-loader--2_0_1","type":"indirect"},"to":{"type":"tarball","url":"https://registry.npmjs.org/vue-loader/-/vue-loader-2.0.1.tgz"}},{"fetchInfo":{"narHash":"sha256-0OdFCS8aMBg/vo/zALjoC8KUdEbDwuoMFV3LsuFuw7A="},"from":{"id":"vue-loader--2_0_2","type":"indirect"},"to":{"type":"tarball","url":"https://registry.npmjs.org/vue-loader/-/vue-loader-2.0.2.tgz"}},{"fetchInfo":{"narHash":"sha256-DGOMvkBYNQFoFSd2qWS96lZYHOUY+tbekV3zErwxVQI="},"from":{"id":"vue-loader--2_0_3","type":"indirect"},"to":{"type":"tarball","url":"https://registry.npmjs.org/vue-loader/-/vue-loader-2.0.3.tgz"}},{"fetchInfo":{"narHash":"sha256-WRsXS0POSrBadup2LhPdBPJmwIeavpI3IU/s59eUhT4="},"from":{"id":"vue-loader--2_1_0","type":"indirect"},"to":{"type":"tarball","url":"https://registry.npmjs.org/vue-loader/-/vue-loader-2.1.0.tgz"}},{"fetchInfo":{"narHash":"sha256-dVWlhNULIZpMySJHcPEb6QT024D3k7A93dO6bNo5QvY="},"from":{"id":"vue-loader--2_1_1","type":"indirect"},"to":{"type":"tarball","url":"https://registry.npmjs.org/vue-loader/-/vue-loader-2.1.1.tgz"}},{"fetchInfo":{"narHash":"sha256-7Wb1I+2I8rVtHMCDZOzx76YTo0nOSiXDXPC/fpHdxO8="},"from":{"id":"vue-loader--3_0_2","type":"indirect"},"to":{"type":"tarball","url":"https://registry.npmjs.org/vue-loader/-/vue-loader-3.0.2.tgz"}},{"fetchInfo":{"narHash":"sha256-4rwywCUO/CkIQvueoK3qeulvSwdZtCrz7v60KjFyMRg="},"from":{"id":"vue-loader--3_0_3","type":"indirect"},"to":{"type":"tarball","url":"https://registry.npmjs.org/vue-loader/-/vue-loader-3.0.3.tgz"}},{"fetchInfo":{"narHash":"sha256-/zEwRKMRe19OvAxILLQfDWCr3OrEBO1IP//7G71FXoY="},"from":{"id":"vue-loader--3_0_4","type":"indirect"},"to":{"type":"tarball","url":"https://registry.npmjs.org/vue-loader/-/vue-loader-3.0.4.tgz"}},{"fetchInfo":{"narHash":"sha256-3Tb/XJrU5iO6SMaqKThiRDq4hHnRjIl45i1PHUg+otI="},"from":{"id":"vue-loader--4_0_0","type":"indirect"},"to":{"type":"tarball","url":"https://registry.npmjs.org/vue-loader/-/vue-loader-4.0.0.tgz"}},{"fetchInfo":{"narHash":"sha256-fcIlzoT5FN/NwBsnip9F7Rmkv5VvUOM9XSByCOgqgL8="},"from":{"id":"vue-loader--4_0_1","type":"indirect"},"to":{"type":"tarball","url":"https://registry.npmjs.org/vue-loader/-/vue-loader-4.0.1.tgz"}},{"fetchInfo":{"narHash":"sha256-E66Zf8TV1XcUzoyUpBKCBh8oTEtZkCfsUhl1puPSTG8="},"from":{"id":"vue-loader--4_0_10","type":"indirect"},"to":{"type":"tarball","url":"https://registry.npmjs.org/vue-loader/-/vue-loader-4.0.10.tgz"}},{"fetchInfo":{"narHash":"sha256-u4cT0JoVWpyPvhF9sMPfrgK8z3vMzeFrboqpFYKJDqY="},"from":{"id":"vue-loader--4_0_2","type":"indirect"},"to":{"type":"tarball","url":"https://registry.npmjs.org/vue-loader/-/vue-loader-4.0.2.tgz"}},{"fetchInfo":{"narHash":"sha256-fzML/5751oOfUZt2i73RlA3YlUkYHlgD7px4SRWfAmU="},"from":{"id":"vue-loader--4_0_3","type":"indirect"},"to":{"type":"tarball","url":"https://registry.npmjs.org/vue-loader/-/vue-loader-4.0.3.tgz"}},{"fetchInfo":{"narHash":"sha256-JUnxTefrAe1sGDepgsciWET/OU5jPIRfbABm5/lQuR8="},"from":{"id":"vue-loader--4_0_4","type":"indirect"},"to":{"type":"tarball","url":"https://registry.npmjs.org/vue-loader/-/vue-loader-4.0.4.tgz"}},{"fetchInfo":{"narHash":"sha256-qxqfWHWaOi230FWyDZUPtXPgVDA44aTbW5a+zqXR/+c="},"from":{"id":"vue-loader--4_0_5","type":"indirect"},"to":{"type":"tarball","url":"https://registry.npmjs.org/vue-loader/-/vue-loader-4.0.5.tgz"}},{"fetchInfo":{"narHash":"sha256-pUB2oBrf4vO/3g4bQYgdNoKuJ+DQfXTIZlpGo23JSeI="},"from":{"id":"vue-loader--4_0_6","type":"indirect"},"to":{"type":"tarball","url":"https://registry.npmjs.org/vue-loader/-/vue-loader-4.0.6.tgz"}},{"fetchInfo":{"narHash":"sha256-cn8ALBq7Xy6iZTxwx9oBTpain8NmjDU7z01EPxnksv4="},"from":{"id":"vue-loader--4_0_7","type":"indirect"},"to":{"type":"tarball","url":"https://registry.npmjs.org/vue-loader/-/vue-loader-4.0.7.tgz"}},{"fetchInfo":{"narHash":"sha256-8EIDPU+MyWxTMlfIFY2OTbgwTo4vlmj5ocABO6f4gNE="},"from":{"id":"vue-loader--4_0_8","type":"indirect"},"to":{"type":"tarball","url":"https://registry.npmjs.org/vue-loader/-/vue-loader-4.0.8.tgz"}},{"fetchInfo":{"narHash":"sha256-AKc2br0cNzsCshjgedD+Ed0Lip7AcAz+m6WEjJYRKfw="},"from":{"id":"vue-loader--4_0_9","type":"indirect"},"to":{"type":"tarball","url":"https://registry.npmjs.org/vue-loader/-/vue-loader-4.0.9.tgz"}},{"fetchInfo":{"narHash":"sha256-u3/xlOCYISqQ4e9USsxqx0G3neHVYmK0bYWGpD5PCjw="},"from":{"id":"vue-loader--5_0_0","type":"indirect"},"to":{"type":"tarball","url":"https://registry.npmjs.org/vue-loader/-/vue-loader-5.0.0.tgz"}},{"fetchInfo":{"narHash":"sha256-g9bgl+Rc5oVBBCT+0tXQHjCiQJh5+dHsEcAc7Pg/ie8="},"from":{"id":"vue-loader--6_0_0","type":"indirect"},"to":{"type":"tarball","url":"https://registry.npmjs.org/vue-loader/-/vue-loader-6.0.0.tgz"}},{"fetchInfo":{"narHash":"sha256-D0q3fkoDw64Vf3mcsWGIqXA+mRv7BREhBI/gJZKMeuI="},"from":{"id":"vue-loader--6_0_1","type":"indirect"},"to":{"type":"tarball","url":"https://registry.npmjs.org/vue-loader/-/vue-loader-6.0.1.tgz"}},{"fetchInfo":{"narHash":"sha256-WVLuAKC6jCQ83bU/ZfApKZxDZUckHz/UvU+eVat8v60="},"from":{"id":"vue-loader--6_0_2","type":"indirect"},"to":{"type":"tarball","url":"https://registry.npmjs.org/vue-loader/-/vue-loader-6.0.2.tgz"}},{"fetchInfo":{"narHash":"sha256-/vgRG4FK7lbn37Zk0oP3xEEudMLvbUADvrN1xptJZik="},"from":{"id":"vue-loader--6_0_3","type":"indirect"},"to":{"type":"tarball","url":"https://registry.npmjs.org/vue-loader/-/vue-loader-6.0.3.tgz"}},{"fetchInfo":{"narHash":"sha256-OCxcqv9wTZieEdqftJDd6eLhFlB36JIbd8KvyZ7SpSY="},"from":{"id":"vue-loader--6_0_4","type":"indirect"},"to":{"type":"tarball","url":"https://registry.npmjs.org/vue-loader/-/vue-loader-6.0.4.tgz"}},{"fetchInfo":{"narHash":"sha256-sUAYKqfMZSqEh6sSVMFtIMjiYi+hkHaput6e8mb6/Fo="},"from":{"id":"vue-loader--6_0_5","type":"indirect"},"to":{"type":"tarball","url":"https://registry.npmjs.org/vue-loader/-/vue-loader-6.0.5.tgz"}},{"fetchInfo":{"narHash":"sha256-NFzVdqXFtOXtNj19IY77EnmlXRebCDGTZRdKBTvi1wc="},"from":{"id":"vue-loader--6_1_0","type":"indirect"},"to":{"type":"tarball","url":"https://registry.npmjs.org/vue-loader/-/vue-loader-6.1.0.tgz"}},{"fetchInfo":{"narHash":"sha256-7+G2i2tq35QJXUkEry+Yl+1jAZTkCOpBN9H9ZT6t4zI="},"from":{"id":"vue-loader--7_0_0","type":"indirect"},"to":{"type":"tarball","url":"https://registry.npmjs.org/vue-loader/-/vue-loader-7.0.0.tgz"}},{"fetchInfo":{"narHash":"sha256-6/91DoZIkygVMfrQ6zF3Pb6WDepdxNmc9OExLHnM0hU="},"from":{"id":"vue-loader--7_0_1","type":"indirect"},"to":{"type":"tarball","url":"https://registry.npmjs.org/vue-loader/-/vue-loader-7.0.1.tgz"}},{"fetchInfo":{"narHash":"sha256-af38D9zR+7s7iaxzLO9IZDG8cRqE/7+s2e2g8EeOHDg="},"from":{"id":"vue-loader--7_0_2","type":"indirect"},"to":{"type":"tarball","url":"https://registry.npmjs.org/vue-loader/-/vue-loader-7.0.2.tgz"}},{"fetchInfo":{"narHash":"sha256-FwhU1onQ7tceKQvHlJcV0g/2Gib5eUkZMaCB957M0JA="},"from":{"id":"vue-loader--7_0_3","type":"indirect"},"to":{"type":"tarball","url":"https://registry.npmjs.org/vue-loader/-/vue-loader-7.0.3.tgz"}},{"fetchInfo":{"narHash":"sha256-LlJFRDfWQZhey8WZ7n1dOcezBQLnwqw9VCMwJfAlnAw="},"from":{"id":"vue-loader--7_1_0","type":"indirect"},"to":{"type":"tarball","url":"https://registry.npmjs.org/vue-loader/-/vue-loader-7.1.0.tgz"}},{"fetchInfo":{"narHash":"sha256-YO3IR4xRTFCw4BpaCLvXqzCU8Lsqwz/3hL+LWTkRQQA="},"from":{"id":"vue-loader--7_1_1","type":"indirect"},"to":{"type":"tarball","url":"https://registry.npmjs.org/vue-loader/-/vue-loader-7.1.1.tgz"}},{"fetchInfo":{"narHash":"sha256-/HZkH1eeekd8p0fjTjUwHdZO+w60tZwJmudoaLzo0Is="},"from":{"id":"vue-loader--7_1_2","type":"indirect"},"to":{"type":"tarball","url":"https://registry.npmjs.org/vue-loader/-/vue-loader-7.1.2.tgz"}},{"fetchInfo":{"narHash":"sha256-g55BbH3VyNQTDgc8jsm/wkNOBOppArYmS15hcE/HmWU="},"from":{"id":"vue-loader--7_1_3","type":"indirect"},"to":{"type":"tarball","url":"https://registry.npmjs.org/vue-loader/-/vue-loader-7.1.3.tgz"}},{"fetchInfo":{"narHash":"sha256-pmqYm9j2HJdhZwHzPCa1V4vh908BKbnn2LLMV5WtP68="},"from":{"id":"vue-loader--7_1_4","type":"indirect"},"to":{"type":"tarball","url":"https://registry.npmjs.org/vue-loader/-/vue-loader-7.1.4.tgz"}},{"fetchInfo":{"narHash":"sha256-rzezIn8GM24PLQvK/ZLYGuj6jGqigPELxkIVZaGqT9A="},"from":{"id":"vue-loader--7_1_5","type":"indirect"},"to":{"type":"tarball","url":"https://registry.npmjs.org/vue-loader/-/vue-loader-7.1.5.tgz"}},{"fetchInfo":{"narHash":"sha256-zd4mPBL+gm3Pplw/GDtkcP3gyv1LgkyHdcjGydMKjQs="},"from":{"id":"vue-loader--7_1_6","type":"indirect"},"to":{"type":"tarball","url":"https://registry.npmjs.org/vue-loader/-/vue-loader-7.1.6.tgz"}},{"fetchInfo":{"narHash":"sha256-XAlsoAZqPVKA7s2alBf/O2jdgas60He5veLrAFzkm0U="},"from":{"id":"vue-loader--7_1_7","type":"indirect"},"to":{"type":"tarball","url":"https://registry.npmjs.org/vue-loader/-/vue-loader-7.1.7.tgz"}},{"fetchInfo":{"narHash":"sha256-9DvLFxOYuyXNsJs1PE9mHyyC30SUIChMaz2hs5mDuYQ="},"from":{"id":"vue-loader--7_1_8","type":"indirect"},"to":{"type":"tarball","url":"https://registry.npmjs.org/vue-loader/-/vue-loader-7.1.8.tgz"}},{"fetchInfo":{"narHash":"sha256-967IxSV+eL1K+Pl4fsTapj0PIoqst8BCHBquiVkmdtc="},"from":{"id":"vue-loader--7_2_0","type":"indirect"},"to":{"type":"tarball","url":"https://registry.npmjs.org/vue-loader/-/vue-loader-7.2.0.tgz"}},{"fetchInfo":{"narHash":"sha256-z9JlnJF+Zd8lYfIbqHi7HlbQBpyk1AUjvHav0FDFSDM="},"from":{"id":"vue-loader--7_3_0","type":"indirect"},"to":{"type":"tarball","url":"https://registry.npmjs.org/vue-loader/-/vue-loader-7.3.0.tgz"}},{"fetchInfo":{"narHash":"sha256-4RkUJyCS7NrbykBLh1tCLCX/OmHToW7Em2IhtHTe3pQ="},"from":{"id":"vue-loader--7_4_0","type":"indirect"},"to":{"type":"tarball","url":"https://registry.npmjs.org/vue-loader/-/vue-loader-7.4.0.tgz"}},{"fetchInfo":{"narHash":"sha256-HHMUoBI2yQL55FQ3/ZEtQWkzQjSRwaiUyazYeJfh398="},"from":{"id":"vue-loader--7_4_1","type":"indirect"},"to":{"type":"tarball","url":"https://registry.npmjs.org/vue-loader/-/vue-loader-7.4.1.tgz"}},{"fetchInfo":{"narHash":"sha256-xVS94VWZ4l6NlPAlYS9SAXYYJjoU2Bz5w/ugJ6b8unU="},"from":{"id":"vue-loader--7_4_2","type":"indirect"},"to":{"type":"tarball","url":"https://registry.npmjs.org/vue-loader/-/vue-loader-7.4.2.tgz"}},{"fetchInfo":{"narHash":"sha256-xsqi1UGCQxzZPryXeTMIb7lqkKL5siSwkDZYw/D8N0A="},"from":{"id":"vue-loader--7_5_0","type":"indirect"},"to":{"type":"tarball","url":"https://registry.npmjs.org/vue-loader/-/vue-loader-7.5.0.tgz"}},{"fetchInfo":{"narHash":"sha256-0qTJzbrTdnCLapPW5tS7dyUNnB5A5WmltgYWXvskAQk="},"from":{"id":"vue-loader--7_5_1","type":"indirect"},"to":{"type":"tarball","url":"https://registry.npmjs.org/vue-loader/-/vue-loader-7.5.1.tgz"}},{"fetchInfo":{"narHash":"sha256-4DEpjiSGPWjcHG0StES4cYmn7SyXXCGQ20naH6KYiHI="},"from":{"id":"vue-loader--7_5_2","type":"indirect"},"to":{"type":"tarball","url":"https://registry.npmjs.org/vue-loader/-/vue-loader-7.5.2.tgz"}},{"fetchInfo":{"narHash":"sha256-59r1ZNqsqtMN6b6Q0KqpRFOup5rbVpgisUjWni3IW3s="},"from":{"id":"vue-loader--7_5_3","type":"indirect"},"to":{"type":"tarball","url":"https://registry.npmjs.org/vue-loader/-/vue-loader-7.5.3.tgz"}},{"fetchInfo":{"narHash":"sha256-2Wl/9HbQc4U9QpqyK410DlOgHHKrzP2Rg9YInrygrmE="},"from":{"id":"vue-loader--8_0_0","type":"indirect"},"to":{"type":"tarball","url":"https://registry.npmjs.org/vue-loader/-/vue-loader-8.0.0.tgz"}},{"fetchInfo":{"narHash":"sha256-o0mqpytnMvaR/UvDbrpV7HULQw8IE1IxJYgalmg+o5U="},"from":{"id":"vue-loader--8_0_1","type":"indirect"},"to":{"type":"tarball","url":"https://registry.npmjs.org/vue-loader/-/vue-loader-8.0.1.tgz"}},{"fetchInfo":{"narHash":"sha256-wNNe0fFu/9mkcUC+ni0GjhajxhxJWmJ0yXi9PfsHbf8="},"from":{"id":"vue-loader--8_0_2","type":"indirect"},"to":{"type":"tarball","url":"https://registry.npmjs.org/vue-loader/-/vue-loader-8.0.2.tgz"}},{"fetchInfo":{"narHash":"sha256-i+pk9EMdC7pisnsgQ1SMatCEOVB6sqHgn3MBgM+POkQ="},"from":{"id":"vue-loader--8_0_3","type":"indirect"},"to":{"type":"tarball","url":"https://registry.npmjs.org/vue-loader/-/vue-loader-8.0.3.tgz"}},{"fetchInfo":{"narHash":"sha256-cxogiwuHbIkFjg1+BrUkmp5FYxh01qF2cJ1J4g+fTxo="},"from":{"id":"vue-loader--8_0_4","type":"indirect"},"to":{"type":"tarball","url":"https://registry.npmjs.org/vue-loader/-/vue-loader-8.0.4.tgz"}},{"fetchInfo":{"narHash":"sha256-TTA209xqEZ33eSYQu1+X+mFhY3AeW0mBR3l+nbPk4Pk="},"from":{"id":"vue-loader--8_0_5","type":"indirect"},"to":{"type":"tarball","url":"https://registry.npmjs.org/vue-loader/-/vue-loader-8.0.5.tgz"}},{"fetchInfo":{"narHash":"sha256-XDc0Roc+jzUsheLu11byu7qaWK4VZl0jOvQ8rlqnWb0="},"from":{"id":"vue-loader--8_1_0","type":"indirect"},"to":{"type":"tarball","url":"https://registry.npmjs.org/vue-loader/-/vue-loader-8.1.0.tgz"}},{"fetchInfo":{"narHash":"sha256-SP+QKt+nAk5ouuAa/fB98nWdzltCxjkZgk67sDi/F9U="},"from":{"id":"vue-loader--8_1_1","type":"indirect"},"to":{"type":"tarball","url":"https://registry.npmjs.org/vue-loader/-/vue-loader-8.1.1.tgz"}},{"fetchInfo":{"narHash":"sha256-6GZm6tgPh+MCBu1yt2Qiyx6y+xWxmRpO9BuOhbImZng="},"from":{"id":"vue-loader--8_1_2","type":"indirect"},"to":{"type":"tarball","url":"https://registry.npmjs.org/vue-loader/-/vue-loader-8.1.2.tgz"}},{"fetchInfo":{"narHash":"sha256-T8IFRQD4sofyrPrc5VPy+egJB4youN27tR5Mo6IOGfY="},"from":{"id":"vue-loader--8_1_3","type":"indirect"},"to":{"type":"tarball","url":"https://registry.npmjs.org/vue-loader/-/vue-loader-8.1.3.tgz"}},{"fetchInfo":{"narHash":"sha256-1SoUtoxOXXKDtmN/UjLRUYrESe2UdFRk0xF82j2DX/w="},"from":{"id":"vue-loader--8_1_4","type":"indirect"},"to":{"type":"tarball","url":"https://registry.npmjs.org/vue-loader/-/vue-loader-8.1.4.tgz"}},{"fetchInfo":{"narHash":"sha256-+n4mCBjK4cscw8CzXOh7vooAReC5csUJUnExNCtsUiQ="},"from":{"id":"vue-loader--8_2_0","type":"indirect"},"to":{"type":"tarball","url":"https://registry.npmjs.org/vue-loader/-/vue-loader-8.2.0.tgz"}},{"fetchInfo":{"narHash":"sha256-VQspD7EEGWRO4C29rP2v4zi6ojujG499hvNXcQ9w4kg="},"from":{"id":"vue-loader--8_2_1","type":"indirect"},"to":{"type":"tarball","url":"https://registry.npmjs.org/vue-loader/-/vue-loader-8.2.1.tgz"}},{"fetchInfo":{"narHash":"sha256-3noMN3QohhiNWbqUrqEpwaVy86hDi216UkYP/M9ezO8="},"from":{"id":"vue-loader--8_2_2","type":"indirect"},"to":{"type":"tarball","url":"https://registry.npmjs.org/vue-loader/-/vue-loader-8.2.2.tgz"}},{"fetchInfo":{"narHash":"sha256-gGDf6sICmNOgVrnnI/kZPrDFkGLwMnII/ZPIhHy56yg="},"from":{"id":"vue-loader--8_2_3","type":"indirect"},"to":{"type":"tarball","url":"https://registry.npmjs.org/vue-loader/-/vue-loader-8.2.3.tgz"}},{"fetchInfo":{"narHash":"sha256-WbyXd9N/aWdXd7HRshlBVhJckAbqwQKt6OGs5nB7bzY="},"from":{"id":"vue-loader--8_3_0","type":"indirect"},"to":{"type":"tarball","url":"https://registry.npmjs.org/vue-loader/-/vue-loader-8.3.0.tgz"}},{"fetchInfo":{"narHash":"sha256-OZKg8PlFSRWM2u6yfn+dptLNc+xVO3vzxqKXJ0shQl8="},"from":{"id":"vue-loader--8_3_1","type":"indirect"},"to":{"type":"tarball","url":"https://registry.npmjs.org/vue-loader/-/vue-loader-8.3.1.tgz"}},{"fetchInfo":{"narHash":"sha256-+cdUsE4n1elDl70foddRPCRRJD8kGm4/n08tUX5tNIY="},"from":{"id":"vue-loader--8_4_0","type":"indirect"},"to":{"type":"tarball","url":"https://registry.npmjs.org/vue-loader/-/vue-loader-8.4.0.tgz"}},{"fetchInfo":{"narHash":"sha256-NIjPndzX9n0xYmR49A7QmX3TSI+MWuq1fJc0VXtBVko="},"from":{"id":"vue-loader--8_5_0","type":"indirect"},"to":{"type":"tarball","url":"https://registry.npmjs.org/vue-loader/-/vue-loader-8.5.0.tgz"}},{"fetchInfo":{"narHash":"sha256-EK4e1rKWSsP03wJdn8C37aAk8ke1q7onDX8zpM0nVsc="},"from":{"id":"vue-loader--8_5_1","type":"indirect"},"to":{"type":"tarball","url":"https://registry.npmjs.org/vue-loader/-/vue-loader-8.5.1.tgz"}},{"fetchInfo":{"narHash":"sha256-FkSAfZO+pIhFoeUPDPB43+LeMfh7x+FS5two6D2noi0="},"from":{"id":"vue-loader--8_5_2","type":"indirect"},"to":{"type":"tarball","url":"https://registry.npmjs.org/vue-loader/-/vue-loader-8.5.2.tgz"}},{"fetchInfo":{"narHash":"sha256-6wnURDPMwy/VERPXrbl7ZM58giBeLYLJwO+mCpl1bb8="},"from":{"id":"vue-loader--8_5_3","type":"indirect"},"to":{"type":"tarball","url":"https://registry.npmjs.org/vue-loader/-/vue-loader-8.5.3.tgz"}},{"fetchInfo":{"narHash":"sha256-8FwRRcjeyaK/u4Dr7zNeff90kAsXhKXT23ViasF84Q0="},"from":{"id":"vue-loader--8_5_4","type":"indirect"},"to":{"type":"tarball","url":"https://registry.npmjs.org/vue-loader/-/vue-loader-8.5.4.tgz"}},{"fetchInfo":{"narHash":"sha256-eK/M1OOAZtoKwoSkIcAftpIOhFKfCfE+Wp7ovwmvvNo="},"from":{"id":"vue-loader--8_6_0","type":"indirect"},"to":{"type":"tarball","url":"https://registry.npmjs.org/vue-loader/-/vue-loader-8.6.0.tgz"}},{"fetchInfo":{"narHash":"sha256-hQ+Uf3O2MNlxrwsgqtOV1HYb0SuX04YwefLhxU7U+gw="},"from":{"id":"vue-loader--8_6_1","type":"indirect"},"to":{"type":"tarball","url":"https://registry.npmjs.org/vue-loader/-/vue-loader-8.6.1.tgz"}},{"fetchInfo":{"narHash":"sha256-hzswWlJ/d8/V0V4xVebu6EJypo55IJohXa1Xnfybt68="},"from":{"id":"vue-loader--8_7_0","type":"indirect"},"to":{"type":"tarball","url":"https://registry.npmjs.org/vue-loader/-/vue-loader-8.7.0.tgz"}},{"fetchInfo":{"narHash":"sha256-uQsdzyzt+GCCd5tnzZegGviJ2jHn5liiha7iu+rWA3A="},"from":{"id":"vue-loader--8_7_1","type":"indirect"},"to":{"type":"tarball","url":"https://registry.npmjs.org/vue-loader/-/vue-loader-8.7.1.tgz"}},{"fetchInfo":{"narHash":"sha256-23I/EX6DYo9VQQTwqzECxnMd/M0cbee24pKLPx8ewCw="},"from":{"id":"vue-loader--9_0_0","type":"indirect"},"to":{"type":"tarball","url":"https://registry.npmjs.org/vue-loader/-/vue-loader-9.0.0.tgz"}},{"fetchInfo":{"narHash":"sha256-mF1gKtdIDjXHO0WupmV19krMe6lpyyKLuixT38ky6dM="},"from":{"id":"vue-loader--9_0_1","type":"indirect"},"to":{"type":"tarball","url":"https://registry.npmjs.org/vue-loader/-/vue-loader-9.0.1.tgz"}},{"fetchInfo":{"narHash":"sha256-rcOlEld8arQC0zqnqX9Dh42tSDyM8jzZ3lS/ZTmhmpo="},"from":{"id":"vue-loader--9_0_2","type":"indirect"},"to":{"type":"tarball","url":"https://registry.npmjs.org/vue-loader/-/vue-loader-9.0.2.tgz"}},{"fetchInfo":{"narHash":"sha256-RFDkxYhUUt8KGxYKhr+OoVkvnRT2Le8nZYWnToxuP1w="},"from":{"id":"vue-loader--9_0_3","type":"indirect"},"to":{"type":"tarball","url":"https://registry.npmjs.org/vue-loader/-/vue-loader-9.0.3.tgz"}},{"fetchInfo":{"narHash":"sha256-botDvmhzTDCqoDu63xWfadYn+Cp8fSpjAtb4wQfXeHo="},"from":{"id":"vue-loader--9_1_0","type":"indirect"},"to":{"type":"tarball","url":"https://registry.npmjs.org/vue-loader/-/vue-loader-9.1.0.tgz"}},{"fetchInfo":{"narHash":"sha256-BfUmZQ5UxRC/nhJIhjtNQUV5yGXo1Q5j6RqH+KGHZHQ="},"from":{"id":"vue-loader--9_1_1","type":"indirect"},"to":{"type":"tarball","url":"https://registry.npmjs.org/vue-loader/-/vue-loader-9.1.1.tgz"}},{"fetchInfo":{"narHash":"sha256-CC/2LATEzMsDDN9yAaxuwquO+FDy6Gl02PG5J+8dwqg="},"from":{"id":"vue-loader--9_1_2","type":"indirect"},"to":{"type":"tarball","url":"https://registry.npmjs.org/vue-loader/-/vue-loader-9.1.2.tgz"}},{"fetchInfo":{"narHash":"sha256-+N/js5PaZkK4M3/JZ7MwWGAavQQMVmd85EHO2q/MP8w="},"from":{"id":"vue-loader--9_1_3","type":"indirect"},"to":{"type":"tarball","url":"https://registry.npmjs.org/vue-loader/-/vue-loader-9.1.3.tgz"}},{"fetchInfo":{"narHash":"sha256-95mTQYkO1SGL5F61aQbGqJSqlonpRZ1g/mdEZK+KxUc="},"from":{"id":"vue-loader--9_2_0","type":"indirect"},"to":{"type":"tarball","url":"https://registry.npmjs.org/vue-loader/-/vue-loader-9.2.0.tgz"}},{"fetchInfo":{"narHash":"sha256-kCZ+H7+Va3FAzll+EMkwJiFGtIFYL3byQF3UIAkRcE0="},"from":{"id":"vue-loader--9_2_1","type":"indirect"},"to":{"type":"tarball","url":"https://registry.npmjs.org/vue-loader/-/vue-loader-9.2.1.tgz"}},{"fetchInfo":{"narHash":"sha256-1KwJwylClwK+PLOTTaMr7kXi25CrFI8yC7d8Q/Vs4cs="},"from":{"id":"vue-loader--9_2_2","type":"indirect"},"to":{"type":"tarball","url":"https://registry.npmjs.org/vue-loader/-/vue-loader-9.2.2.tgz"}},{"fetchInfo":{"narHash":"sha256-xjDZ0FmPQzJj61ix28RbKt4/l1v4ltDWNu4VYz4T2Kg="},"from":{"id":"vue-loader--9_2_3","type":"indirect"},"to":{"type":"tarball","url":"https://registry.npmjs.org/vue-loader/-/vue-loader-9.2.3.tgz"}},{"fetchInfo":{"narHash":"sha256-6+7ZqU9Fy88wTKNQRqaRlsZNRV0J0oi9XqBq3YBZcn4="},"from":{"id":"vue-loader--9_3_0","type":"indirect"},"to":{"type":"tarball","url":"https://registry.npmjs.org/vue-loader/-/vue-loader-9.3.0.tgz"}},{"fetchInfo":{"narHash":"sha256-tr0AGtUVs4kgy9yYCzC/NmWkr4s+lLHjcEWmr+J4Pvo="},"from":{"id":"vue-loader--9_3_1","type":"indirect"},"to":{"type":"tarball","url":"https://registry.npmjs.org/vue-loader/-/vue-loader-9.3.1.tgz"}},{"fetchInfo":{"narHash":"sha256-VOfwWKEp5d9Tjb1oRaV+qRyZuBf5i4WPgrHZj/MhDzs="},"from":{"id":"vue-loader--9_3_2","type":"indirect"},"to":{"type":"tarball","url":"https://registry.npmjs.org/vue-loader/-/vue-loader-9.3.2.tgz"}},{"fetchInfo":{"narHash":"sha256-2xfyo8+BhCZ9jzff0BUEkhJ5sC4zOvKiujplvU0tnLo="},"from":{"id":"vue-loader--9_4_0","type":"indirect"},"to":{"type":"tarball","url":"https://registry.npmjs.org/vue-loader/-/vue-loader-9.4.0.tgz"}},{"fetchInfo":{"narHash":"sha256-eB+WyB1T56ZZsRUmBh3AWBC4jkWRvfaMcYYG280RYdM="},"from":{"id":"vue-loader--9_4_1","type":"indirect"},"to":{"type":"tarball","url":"https://registry.npmjs.org/vue-loader/-/vue-loader-9.4.1.tgz"}},{"fetchInfo":{"narHash":"sha256-Z6Dui9hRHV9RsDwit1Bg7qGa7hKHa9DXlNJnVoLRM5E="},"from":{"id":"vue-loader--9_4_2","type":"indirect"},"to":{"type":"tarball","url":"https://registry.npmjs.org/vue-loader/-/vue-loader-9.4.2.tgz"}},{"fetchInfo":{"narHash":"sha256-9OuUZpZgoytFSDR/qMC547OWd5+WichGZRMCj+hRKhE="},"from":{"id":"vue-loader--9_5_0","type":"indirect"},"to":{"type":"tarball","url":"https://registry.npmjs.org/vue-loader/-/vue-loader-9.5.0.tgz"}},{"fetchInfo":{"narHash":"sha256-Wu8KfMw37PqnFdUrhDAz+qE8JEUCys7/oNdenFvrIpU="},"from":{"id":"vue-loader--9_5_1","type":"indirect"},"to":{"type":"tarball","url":"https://registry.npmjs.org/vue-loader/-/vue-loader-9.5.1.tgz"}},{"fetchInfo":{"narHash":"sha256-FItwmol/zzAi4vBF68DG7Jq77kGptQoB5jzyGLpq60k="},"from":{"id":"vue-loader--9_5_2","type":"indirect"},"to":{"type":"tarball","url":"https://registry.npmjs.org/vue-loader/-/vue-loader-9.5.2.tgz"}},{"fetchInfo":{"narHash":"sha256-bMurzGe0k5GyoTrvaVaOpSn+W/sX/qIQzlWXnoyaaII="},"from":{"id":"vue-loader--9_5_3","type":"indirect"},"to":{"type":"tarball","url":"https://registry.npmjs.org/vue-loader/-/vue-loader-9.5.3.tgz"}},{"fetchInfo":{"narHash":"sha256-rCQCY/XLj8xVo8Gjp5eW1Le8fmITc6mXrtFrCgkjBEw="},"from":{"id":"vue-loader--9_6_0","type":"indirect"},"to":{"type":"tarball","url":"https://registry.npmjs.org/vue-loader/-/vue-loader-9.6.0.tgz"}},{"fetchInfo":{"narHash":"sha256-rsF/WqefEbEJkhXqdSIHMTpxw/4VFTSDgzzJaR3/sno="},"from":{"id":"vue-loader--9_7_0","type":"indirect"},"to":{"type":"tarball","url":"https://registry.npmjs.org/vue-loader/-/vue-loader-9.7.0.tgz"}},{"fetchInfo":{"narHash":"sha256-ecZjLxMOJszM0gE3KRWJwVczKl3ugrGffKnJJLW+jmE="},"from":{"id":"vue-loader--9_8_0","type":"indirect"},"to":{"type":"tarball","url":"https://registry.npmjs.org/vue-loader/-/vue-loader-9.8.0.tgz"}},{"fetchInfo":{"narHash":"sha256-pUyLCoh0W5QzDExl3Ll5quaGMqrTTPzGu5WhM6I0Bqo="},"from":{"id":"vue-loader--9_8_1","type":"indirect"},"to":{"type":"tarball","url":"https://registry.npmjs.org/vue-loader/-/vue-loader-9.8.1.tgz"}},{"fetchInfo":{"narHash":"sha256-LEIYpNxbjy7VkXHwAnpgmd5f0mXRMuxT0+rPw1DFMUE="},"from":{"id":"vue-loader--9_9_0","type":"indirect"},"to":{"type":"tarball","url":"https://registry.npmjs.org/vue-loader/-/vue-loader-9.9.0.tgz"}},{"fetchInfo":{"narHash":"sha256-+O0Vp78czPTBmuKR1Y18CqfaEeYcZ7RIIxXkxlP+I7M="},"from":{"id":"vue-loader--9_9_1","type":"indirect"},"to":{"type":"tarball","url":"https://registry.npmjs.org/vue-loader/-/vue-loader-9.9.1.tgz"}},{"fetchInfo":{"narHash":"sha256-D0yKPjSKrEWmGhKNEN1EXjLYQHQTP8um2JND+iApevY="},"from":{"id":"vue-loader--9_9_2","type":"indirect"},"to":{"type":"tarball","url":"https://registry.npmjs.org/vue-loader/-/vue-loader-9.9.2.tgz"}},{"fetchInfo":{"narHash":"sha256-4rnIqxg5FJxmt9eapXwv0wurFNd4N2eulu4koe+J3is="},"from":{"id":"vue-loader--9_9_3","type":"indirect"},"to":{"type":"tarball","url":"https://registry.npmjs.org/vue-loader/-/vue-loader-9.9.3.tgz"}},{"fetchInfo":{"narHash":"sha256-7sjoaKy1aXrEsJ1w00qhwBhTUia6VWTp2jFnpxKckXk="},"from":{"id":"vue-loader--9_9_4","type":"indirect"},"to":{"type":"tarball","url":"https://registry.npmjs.org/vue-loader/-/vue-loader-9.9.4.tgz"}},{"fetchInfo":{"narHash":"sha256-xO0uT+5YJfTD3h/zkFROYennW7bY9wyVFSMu0aHk1y4="},"from":{"id":"vue-loader--9_9_5","type":"indirect"},"to":{"type":"tarball","url":"https://registry.npmjs.org/vue-loader/-/vue-loader-9.9.5.tgz"}}]}