{"info":{"lastModifiedDate":"20220629063629","rev":"13-6be2c1295102a3242144d6106bc2bdde"},"treelockVersion":1,"trees":[{"fetchInfo":{"narHash":"sha256-YG16dyndnesA5pWwWBf+iTCaUZf3HaOCTnwqfkgEhDE="},"from":{"id":"yaeti--latest","type":"indirect"},"to":{"type":"tarball","url":"https://registry.npmjs.org/yaeti/-/yaeti-1.0.3.tgz"}},{"fetchInfo":{"narHash":"sha256-TFtBJdN2pyfwe1HPal61cc8iVjp1goO6Z4HelMoDjtk="},"from":{"id":"yaeti--0_0_1","type":"indirect"},"to":{"type":"tarball","url":"https://registry.npmjs.org/yaeti/-/yaeti-0.0.1.tgz"}},{"fetchInfo":{"narHash":"sha256-ltj+KbuuqT6hf2fDIONh/8va2L6YSaO+mgmn+2PejE0="},"from":{"id":"yaeti--0_0_2","type":"indirect"},"to":{"type":"tarball","url":"https://registry.npmjs.org/yaeti/-/yaeti-0.0.2.tgz"}},{"fetchInfo":{"narHash":"sha256-8B3+SXmW8XwnDi9A7aDQyMqPN25/kVaHmIFoZwfODnI="},"from":{"id":"yaeti--0_0_3","type":"indirect"},"to":{"type":"tarball","url":"https://registry.npmjs.org/yaeti/-/yaeti-0.0.3.tgz"}},{"fetchInfo":{"narHash":"sha256-COmH01hwHZiP7QD4WwMfuxuZOU+jyLszl16eU6CuiHU="},"from":{"id":"yaeti--0_0_4","type":"indirect"},"to":{"type":"tarball","url":"https://registry.npmjs.org/yaeti/-/yaeti-0.0.4.tgz"}},{"fetchInfo":{"narHash":"sha256-rEPPW9zeWh7AAHH9Bkl8QUq1ddJnnhJ0lEFES22LEFo="},"from":{"id":"yaeti--0_0_5","type":"indirect"},"to":{"type":"tarball","url":"https://registry.npmjs.org/yaeti/-/yaeti-0.0.5.tgz"}},{"fetchInfo":{"narHash":"sha256-ZMTfW7haaBSP3YkUf7bsOO6q3s2dL2ByupxIcvnwHqY="},"from":{"id":"yaeti--0_0_6","type":"indirect"},"to":{"type":"tarball","url":"https://registry.npmjs.org/yaeti/-/yaeti-0.0.6.tgz"}},{"fetchInfo":{"narHash":"sha256-Bn23Vd83PcLamXrI9WYhStuNKzclkw2MqHfD6PKhpE4="},"from":{"id":"yaeti--1_0_0","type":"indirect"},"to":{"type":"tarball","url":"https://registry.npmjs.org/yaeti/-/yaeti-1.0.0.tgz"}},{"fetchInfo":{"narHash":"sha256-dSjY8kU1tI6J3b5tIlH5ZdSrdiaJYwJS6BBuXVqTc9Q="},"from":{"id":"yaeti--1_0_1","type":"indirect"},"to":{"type":"tarball","url":"https://registry.npmjs.org/yaeti/-/yaeti-1.0.1.tgz"}},{"fetchInfo":{"narHash":"sha256-fabtxu/Xpjuciu7tMxUf6UYSOEiFbkOmldu8IF75cuA="},"from":{"id":"yaeti--1_0_2","type":"indirect"},"to":{"type":"tarball","url":"https://registry.npmjs.org/yaeti/-/yaeti-1.0.2.tgz"}},{"fetchInfo":{"narHash":"sha256-YG16dyndnesA5pWwWBf+iTCaUZf3HaOCTnwqfkgEhDE="},"from":{"id":"yaeti--1_0_3","type":"indirect"},"to":{"type":"tarball","url":"https://registry.npmjs.org/yaeti/-/yaeti-1.0.3.tgz"}}]}